Workbook

Sheet City ​​of Madrid
B2: Company | C2: Type | D2: Infrastructure | E2: Type Infrastructure | F2: City | G2: Zip Code | H2: Location | I2: Address | J2: Latitude | K2: Longitude
B4: InPost | C4: Lockers | D4: Private | E4: Supermarket | F4: Madrid | G4: 28001 | H4: Supermercado Dia | I4: Calle de Nuñez de Balboa, 32 | J4: 40.425934 | K4: -3.6820859
B5: InPost | C5: Lockers | D5: Private | E5: Parking | F5: Madrid | G5: 28001 | H5: 24/7 Parking Ayala Grupo | I5: Cl. de Ayala, 38 | J5: 40.427876 | K5: -3.6845761
B6: InPost | C6: Convenience stores | D6: Private | E6: Premises | F6: Madrid | G6: 28001 | H6: Grupo Hicorsa Artes Graficas | I6: Calle de Goya, 43 | J6: 40.425425 | K6: -3.6829045
B7: InPost | C7: Convenience stores | D7: Private | E7: Premises | F7: Madrid | G7: 28001 | H7: Panaderia Alimentacion Lagasca | I7: Calle de Lagasca, 6 | J7: 40.421287 | K7: -3.6855704
B8: InPost | C8: Convenience stores | D8: Private | E8: Premises | F8: Madrid | G8: 28001 | H8: Jesus Rodriguez Cuadros | I8: C. de Alcalá, 99 | J8: 40.421684 | K8: -3.683567
B9: InPost | C9: Convenience stores | D9: Private | E9: Premises | F9: Madrid | G9: 28001 | H9: La Capital | I9: Calle del Gral. Pardiñas, 3 | J9: 40.424026 | K9: -3.6788843
B10: InPost | C10: Convenience stores | D10: Private | E10: Premises | F10: Madrid | G10: 28001 | H10: Take Up | I10: Calle del Gral. Pardiñas, 31 | J10: 40.427107 | K10: -3.6787459
B11: InPost | C11: Lockers | D11: Public | E11: Parking | F11: Madrid | G11: 28001 | H11: 24/7 Emt Parking Recoletos | I11: P.º de Recoletos, 4 | J11: 40.420739 | K11: -3.6918522
B12: InPost | C12: Lockers | D12: Private | E12: Supermarket | F12: Madrid | G12: 28002 | H12: Locker Eroski City Sanchez Pach | I12: C. de Sánchez Pacheco | J12: 40.447746 | K12: -3.6723477
B13: InPost | C13: Convenience stores | D13: Private | E13: Premises | F13: Madrid | G13: 28002 | H13: Moran Opticos | I13: C. de López de Hoyos, 128 | J13: 40.445154 | K13: -3.6734021
B14: InPost | C14: Convenience stores | D14: Private | E14: Premises | F14: Madrid | G14: 28002 | H14: Herbolario Sana Sana | I14: C. de Pradillo, 7 | J14: 40.44896 | K14: -3.6754966
B15: InPost | C15: Convenience stores | D15: Private | E15: Premises | F15: Madrid | G15: 28002 | H15: Locutorio Robert Multiservices | I15: C. de Vinaroz, 2 | J15: 40.444972 | K15: -3.6750507
B16: InPost | C16: Convenience stores | D16: Private | E16: Premises | F16: Madrid | G16: 28002 | H16: Optica Golf | I16: C. del Príncipe de Vergara 2 | J16: 40.441907 | K16: -3.6785344
B17: InPost | C17: Lockers | D17: Private | E17: Supermarket | F17: Madrid | G17: 28002 | H17: Supermercado Dia | I17: C. de Eugenio Salazar, 27 | J17: 40.446448 | K17: -3.6748581
B18: InPost | C18: Convenience stores | D18: Private | E18: Premises | F18: Madrid | G18: 28002 | H18: Mioptico Lopez De Hoyos | I18: C. de López de Hoyos, 135 | J18: 40.447289 | K18: -3.6697828
... B28: InPost | C28: Convenience stores | D28: Private | E28: Premises | F28: Madrid | G28: 28003 | H28: La Tienda De Almudena | I28: Calle de Zurbano, 93 | J28: 40.44094 | K28: -3.6927401
B29: InPost | C29: Convenience stores | D29: Private | E29: Premises | F29: Madrid | G29: 28003 | H29: Mis Miss | I29: C. de Alonso Cano, 91 | J29: 40.444357 | K29: -3.6973242
B30: InPost | C30: Convenience stores | D30: Private | E30: Premises | F30: Madrid | G30: 28003 | H30: Baez Locutorio | I30: C. de Espronceda, 9 | J30: 40.441101 | K30: -3.698141
B31: InPost | C31: Convenience stores | D31: Private | E31: Premises | F31: Madrid | G31: 28003 | H31: Barullo Company | I31: Calle de Sta Engracia, 131 | J31: 40.442444 | K31: -3.702151
B32: InPost | C32: Convenience stores | D32: Private | E32: Premises | F32: Madrid | G32: 28003 | H32: Expendeduria 791 | I32: C/ de Ponzano, 25 | J32: 40.439226 | K32: -3.699629
B33: InPost | C33: Lockers | D33: Private | E33: Parking | F33: Madrid | G33: 28003 | H33: Locker 24/7 Parking Empark Ponz | I33: C. de Alenza, 18 | J33: 40.444416 | K33: -3.7004759
B34: InPost | C34: Lockers | D34: Private | E34: Premises | F34: Madrid | G34: 28003 | H34: Money Exchang | I34: C. de Raimundo Fernández Villaverde, 13 | J34: 40.447222 | K34: -3.7021532
B35: InPost | C35: Convenience stores | D35: Private | E35: Premises | F35: Madrid | G35: 28003 | H35: Bicicletas Y Calzado | I35: Av. de la Reina Victoria, 51 | J35: 40.446443 | K35: -3.7120553
B36: InPost | C36: Convenience stores | D36: Private | E36: Premises | F36: Madrid | G36: 28004 | H36: Nails Nactory Santa Barbara | I36: C. de Sta. Bárbara, 7 | J36: 40.424252 | K36: -3.7012663
B37: InPost | C37: Convenience stores | D37: Private | E37: Premises | F37: Madrid | G37: 28004 | H37: El Jardin De Churruca | I37: C. de Churruca, 19 | J37: 40.428212 | K37: -3.701358
B38: InPost | C38: Convenience stores | D38: Private | E38: Premises | F38: Madrid | G38: 28004 | H38: Dirtypop | I38: C. de Gravina, 1 | J38: 40.423612 | K38: -3.6985475
B39: InPost | C39: Convenience stores | D39: Private | E39: Premises | F39: Madrid | G39: 28004 | H39: Fotocopias Javipar | I39: C. de Loreto y Chicote, 13 | J39: 40.421742 | K39: -3.7044434
B40: InPost | C40: Convenience stores | D40: Private | E40: Premises | F40: Madrid | G40: 28004 | H40: Ixion Man | I40: C. de Pelayo, 9 | J40: 40.422519 | K40: -3.6991006
B41: InPost | C41: Convenience stores | D41: Private | E41: Premises | F41: Madrid | G41: 28004 | H41: El Jardin De Kika | I41: C. del Pez, 12 | J41: 40.423535 | K41: -3.7047451
B42: InPost | C42: Convenience stores | D42: Private | E42: Premises | F42: Madrid | G42: 28004 | H42: Copypez 12 | I42: C. del Pez, 12 | J42: 40.423629 | K42: -3.7048692
B43: InPost | C43: Lockers | D43: Private | E43: Parking | F43: Madrid | G43: 28004 | H43: 24/7 Parking Apk2 Plaza | I43: Plaza del Rey s/n | J43: 40.420326 | K43: -3.6961696
B44: InPost | C44: Convenience stores | D44: Private | E44: Premises | F44: Madrid | G44: 28004 | H44: The Mad Plug | I44: C. de Valverde, 35 | J44: 40.423223 | K44: -3.7018485
B45: InPost | C45: Convenience stores | D45: Private | E45: Premises | F45: Madrid | G45: 28004 | H45: Pcservice | I45: Cl. del Marqués de Sta. Ana | J45: 40.424638 | K45: -3.7049473
B46: InPost | C46: Lockers | D46: Private | E46: Premises | F46: Madrid | G46: 28004 | H46: Money Exchange Fuencarral | I46: Calle de Fuencarral & C. de las Infantas | J46: 40.421388 | K46: -3.7012384
B47: InPost | C47: Convenience stores | D47: Private | E47: Parking | F47: Madrid | G47: 28005 | H47: Locker Parking Latina | I47: C. de Toledo, 88 | J47: 40.408826 | K47: -3.7109194
B48: InPost | C48: Convenience stores | D48: Private | E48: Premises | F48: Madrid | G48: 28005 | H48: Golochuches | I48: C. de Melilla, 39 | J48: 40.400647 | K48: -3.7103177
B49: InPost | C49: Convenience stores | D49: Private | E49: Premises | F49: Madrid | G49: 28005 | H49: Estanco Piramides | I49: P.º de las Acacias, 69 | J49: 40.401131 | K49: -3.7132209
B50: InPost | C50: Convenience stores | D50: Private | E50: Premises | F50: Madrid | G50: 28005 | H50: Nuvole Di Profumo Mercado De La | I50: Pl. de la Cebada, S/N | J50: 40.41121 | K50: -3.7099362
B51: InPost | C51: Convenience stores | D51: Private | E51: Premises | F51: Madrid | G51: 28005 | H51: Optica Piramides | I51: P.º de Juan Antonio Vallejo-Nájera Botas | J51: 40.402114 | K51: -3.7080329
B52: InPost | C52: Convenience stores | D52: Private | E52: Premises | F52: Madrid | G52: 28005 | H52: Mioptico Embajadores | I52: C. de Martín de Vargas, 2 | J52: 40.404721 | K52: -3.703328
B53: InPost | C53: Lockers | D53: Private | E53: Parking | F53: Madrid | G53: 28005 | H53: Locker 24/7 Grupo Bolton Garage | I53: C/ de la Ribera de Curtidores | J53: 40.407122 | K53: -3.7073202
B54: InPost | C54: Convenience stores | D54: Private | E54: Premises | F54: Madrid | G54: 28005 | H54: Estanco 149 Pasillo Verde | I54: Pasillo Verde, P.º de Juan Antonio Vallejo-Nájera Botas, 50 | J54: 40.405026 | K54: -3.7148186
B55: InPost | C55: Lockers | D55: Public | E55: Parking | F55: Madrid | G55: 28005 | H55: Locker 24/7 Emt Mad Parking San | I55: C. San Epifanio, 9 | J55: 40.40104 | K55: -3.7192906
... B172: InPost | C172: Convenience stores | D172: Private | E172: Premises | F172: Madrid | G172: 28017 | H172: Papeleria Minfi | I172: C. de Emilio Ferrari, 88 | J172: 40.429025 | K172: -3.6395183
B173: InPost | D173: Private | E173: Premises | F173: Madrid | G173: 28017 | H173: Locutorio Y Transporte Orion | I173: C. de Mª Teresa Sáenz de Heredia, 7 | J173: 40.422532 | K173: -3.6546342
B174: InPost | C174: Convenience stores | D174: Private | E174: Premises | F174: Madrid | G174: 28017 | H174: Papeleria Adelfa | I174: C. del Poeta Blas de Otero, 32 | J174: 40.42165 | K174: -3.6517336
B175: InPost | C175: Convenience stores | D175: Private | E175: Premises | F175: Madrid | G175: 28017 | H175: Papeleria Libreria Gonzalo | I175: C/ de José Arcones Gil, 84 | J175: 40.430429 | K175: -3.6359295
B176: InPost | C176: Convenience stores | D176: Private | E176: Premises | F176: Madrid | G176: 28017 | H176: Peluqueria Y Estetica Vilans | I176: Av. de Daroca, 56 | J176: 40.429575 | K176: -3.6536036
B177: InPost | C177: Convenience stores | D177: Private | E177: Premises | F177: Madrid | G177: 28017 | H177: Locutorio El Grande | I177: C. del Río Ulla, 3 | J177: 40.435261 | K177: -3.6428924
B178: InPost | C178: Convenience stores | D178: Private | E178: Premises | F178: Madrid | G178: 28017 | H178: Electric Family | I178: C. de Vital Aza, 48 | J178: 40.432407 | K178: -3.640753
B179: InPost | C179: Convenience stores | D179: Private | E179: Premises | F179: Madrid | G179: 28017 | H179: Foto Rossny | I179: C. de Ricardo Ortiz, 8 | J179: 40.429897 | K179: -3.6582026
B180: InPost | C180: Convenience stores | D180: Private | E180: Premises | F180: Madrid | G180: 28017 | H180: Locutorio Wilson | I180: C. de Vicente Espinel, 3 | J180: 40.436217 | K180: -3.6410559
B181: InPost | C181: Convenience stores | D181: Private | E181: Premises | F181: Madrid | G181: 28017 | H181: Estanco Alcala 234 | I181: C. de Alcalá, 234 | J181: 40.431857 | K181: -3.6573869
B182: InPost | C182: Convenience stores | D182: Private | E182: Premises | F182: Madrid | G182: 28017 | H182: Tribuna Libros | I182: Calle de Portugalete, 17 | J182: 40.427056 | K182: -3.634875
B183: InPost | C183: Convenience stores | D183: Private | E183: Premises | F183: Madrid | G183: 28017 | H183: Bosco Shop | I183: C. de Ricardo Ortiz, 22 | J183: 40.42831 | K183: -3.658208
B184: InPost | C184: Convenience stores | D184: Private | E184: Premises | F184: Madrid | G184: 28017 | H184: Frada Fruit | I184: C. Paredes de Nava, 19 | J184: 40.420325 | K184: -3.6273396
B185: InPost | C185: Convenience stores | D185: Private | E185: Premises | F185: Madrid | G185: 28018 | H185: Cpumania | I185: C. del Arroyo del Olivar, 97 | J185: 40.388502 | K185: -3.6491171
... B3299: Amazon | C3299: Centro de distribución/recepción | D3299: Private | E3299: Industrial estate | F3299: Madrid | G3299: 28823 | H3299: Almacenamiento y preparación pedidos supermercado | I3299: Av. de la Industria, 18, Coslada | J3299: 40.43389 | K3299: -3.5523145
B3300: Amazon | C3300: Almacén/E-fulfilment | D3300: Private | E3300: Industrial estate | F3300: Madrid | G3300: 28804 | I3300: Carr. Nacional II, 20, Alcalá de Henares | J3300: 40.505511 | K3300: -3.3180367
B3301: Amazon | C3301: Centro de distribución/recepción | D3301: Private | E3301: Industrial estate | F3301: Madrid | G3301: 28823 | I3301: Av. de José Gárate, 11, Coslada | J3301: 40.431029 | K3301: -3.5446016
B3302: Correos | C3302: Estación logistica de ultima milla | D3302: Public | E3302: Industrial estate | F3302: Madrid | G3302: 28031 | H3302: CTA Madrid CAM 3 (Recepción, clasificación y envío) | I3302: Cam. de las Hormigueras, 169, Vallecas | J3302: 40.377677 | K3302: -3.6348197
B3303: Correos | C3303: Centros de distribución/recepción | D3303: Public | E3303: Industrial estate | F3303: Madrid | G3303: 28042 | H3303: centro de distribución y consolidación | I3303: C. Alfa, 14, Barajas, Madrid - ADT Gestión Aduanera | J3303: 40.456256 | K3303: -3.5589571
B3304: Correos | C3304: Centros de distribución/recepción | D3304: Public | E3304: Industrial estate | F3304: Madrid | G3304: 28053 | H3304: CTM Madrid (Recepción, clasificación y envío) | I3304: Ctra. Villaverde a Vallecas, Km 3.5, nave S9A, Vallecas | J3304: 40.364316 | K3304: -3.6511917
B3305: Correos | C3305: Centros de distribución/recepción | D3305: Public | E3305: Industrial estate | F3305: Madrid | G3305: 28053 | I3305: CAM-1, Eje 3, 13 - CTM, Madrid | J3305: 40.362131 | K3305: -3.6535695
B3306: Correos | C3306: Centros de distribución/recepción | D3306: Public | E3306: Industrial estate | F3306: Madrid | G3306: 28053 | I3306: CAM-4, Eje 6, 20 - CTM, Madrid | J3306: 40.36391 | K3306: -3.6502103
B3307: Correos | C3307: Estación logistica de ultima milla | D3307: Public | E3307: Industrial estate | F3307: Madrid | G3307: 28036 | I3307: CTL, Hiedra, 7 - Estación de Chamartín | J3307: 40.476796 | K3307: -3.6774465
B3308: Correos Express | C3308: Centros de distribución/recepción | D3308: Public | E3308: Industrial estate | F3308: Madrid | G3308: 28053 | H3308: Centro Correos Exp. Vallecas | I3308: Av. Eje Central, Km 3,500, Nave 6SA, Vallecas | J3308: 40.363322 | K3308: -3.6551092
B3309: Correos Express | C3309: Almacén/E-fulfilment | D3309: Public | E3309: Industrial estate | F3309: Madrid | G3309: 28906 | H3309: Correos Express -Getafe | I3309: C. Calidad, 17, Poligono Industrial los Olivos, Getafe | J3309: 40.315211 | K3309: -3.6793073
B3310: Correos Express | C3310: Centros de distribución/recepción | D3310: Public | E3310: Industrial estate | F3310: Madrid | G3310: 28821 | H3310: Centro Correos Exp. Coslada | I3310: Av. de Europa, 8, Coslada | J3310: 40.43446 | K3310: -3.5601221
B3311: Mondial Relay (Impost) | C3311: Estación logistica de ultima milla | D3311: Private | E3311: Industrial estate | F3311: Madrid | G3311: 28806 | H3311: Centro de distribución urbana o estación de última milla | I3311: C. Tales de Mileto, 19, Alcalá de Henares | J3311: 40.491069 | K3311: -3.396276
B3312: DHL | C3312: Centros de distribución/recepción | D3312: Private | E3312: Industrial estate | F3312: Madrid | G3312: 28042 | H3312: Gestion envíos locales, nacionales e internacionales | I3312: Centro de Carga Aérea, Avda. Central s/n (Aeropuerto Barajas) | J3312: 40.457612 | K3312: -3.5620059
B3313: DHL | C3313: Almacén/E-fulfilment | D3313: Private | E3313: Industrial estate | F3313: Madrid | G3313: 28906 | H3313: Centro de distribución de paquetería | I3313: Area Empresarial Andalucia, Río Almanzora, Sectores 7-8, Getafe | J3313: 40.269517 | K3313: -3.7110007
B3314: DHL | C3314: Centros de distribución/recepción | D3314: Private | E3314: Industrial estate | F3314: Madrid | G3314: 28821 | I3314: C. de Rumanía, 4, Coslada | J3314: 40.438439 | K3314: -3.5499733
B3315: Celeritas | C3315: Centros de distribución/recepción | D3315: Private | E3315: Industrial estate | F3315: Madrid | G3315: 28830 | H3315: Centro de distribución urbana o estación de última milla | I3315: C. de los Vidrieros, 1, San Fernando de Henares | J3315: 40.445803 | K3315: -3.490669
B3316: Celeritas | C3316: Estación logistica de ultima milla | D3316: Private | E3316: Industrial estate | F3316: Madrid | G3316: 28108 | I3316: Av. de Valdelaparra, 29, Alcobendas | J3316: 40.538485 | K3316: -3.6479126
B3317: CTT Express | C3317: Centros de distribución/recepción | D3317: Private | E3317: Industrial estate | F3317: Madrid | G3317: 28821 | H3317: Centro de distribución urbana o estación de última milla | I3317: Av. de Europa, 9, Coslada | J3317: 40.435696 | K3317: -3.5641074
B3318: CTT Express | C3318: Centros de distribución/recepción | D3318: Private | E3318: Industrial estate | F3318: Madrid | G3318: 28830 | H3318: Centro de distribución urbana o estación de última milla | I3318: C. Marcelino Camacho, 13,San Fernando de Henares | J3318: 40.432696 | K3318: -3.4984276
B3319: Mail Boxes ETC | C3319: Estación logistica de ultima milla | D3319: Private | E3319: Industrial estate | F3319: Madrid | G3319: s/d | H3319: Almacenaje, picking, embalaje pedidos, gestión inventario | I3319: s/d | J3319: s/d | K3319: s/d
B3320: GLS | C3320: Estación logistica de ultima milla | D3320: Private | E3320: Industrial estate | F3320: Madrid | G3320: 28823 | H3320: Centro de distribución y consolidación de envíos | I3320: Av. de Fuentemar, 18, Coslada | J3320: 40.432849 | K3320: -3.5480942
B3321: GLS | C3321: Estación logistica de ultima milla | D3321: Private | E3321: Industrial estate | F3321: Madrid | G3321: 28823 | H3321: Centro de distribución urbana o estación de última milla | I3321: C. de la Alcarria, 8, Coslada | J3321: 40.431347 | K3321: -3.5489476
B3322: GLS | C3322: Estación logistica de ultima milla | D3322: Private | E3322: Industrial estate | F3322: Madrid | G3322: 28823 | H3322: Centro de distribución urbana o estación de última milla | I3322: Av. de la Cañada, 64, posterior, Coslada | J3322: 40.438814 | K3322: -3.5403252
B3323: GLS | C3323: Centros de distribución/recepción | D3323: Private | E3323: Industrial estate | F3323: Madrid | G3323: 28830 | I3323: C. de los Fontaneros, 1, San Fernando de Henares | J3323: 40.445706 | K3323: -3.5039656
B3324: MRW | C3324: Centros de distribución/recepción | D3324: Private | E3324: Industrial estate | F3324: Madrid | G3324: 28042 | H3324: Centro de distribución recepción y envío de paquetes | I3324: Av. Central, 24, Barajas | J3324: 40.451741 | K3324: -3.5720723
B3325: MRW | C3325: Centros de distribución/recepción | D3325: Private | E3325: Industrial estate | F3325: Madrid | G3325: 28821 | H3325: Centro de distribución urbana o estación de última milla | I3325: C. Holanda, 1, Coslada | J3325: 40.434782 | K3325: -3.567821
B3326: MRW | C3326: Almacén/E-fulfilment | D3326: Private | E3326: Industrial estate | F3326: Madrid | G3326: 28906 | H3326: Centro de distribución urbana o estación de última milla | I3326: C. Herreros, 8, Getafe | J3326: 40.24845 | K3326: -3.7052352
B3327: MRW | C3327: Estación logistica de ultima milla | D3327: Private | E3327: Industrial estate | F3327: Madrid | G3327: 28053 | I3327: Terminal de Transporte de Mercancías , Méndez Álvaro, 84 | J3327: 40.390525 | K3327: -3.6764262
B3328: UPS | C3328: Centros de distribución/recepción | D3328: Private | E3328: Industrial estate | F3328: Madrid | G3328: 28830 | H3328: HUB Central | I3328: Av. del Sistema Solar, 17, San Fernando de Henares | J3328: 40.450207 | K3328: -3.4975546
B3329: UPS | C3329: Centros de distribución/recepción | D3329: Private | E3329: Industrial estate | F3329: Madrid | G3329: 28820 | H3329: Centro de distribución urbana o estación de última milla | I3329: Avenida de la Cañada 64-66 Módulo F, Coslada | J3329: 40.439107 | K3329: -3.5407967
B3330: UPS | C3330: Centros de distribución/recepción | D3330: Private | E3330: Industrial estate | F3330: Madrid | G3330: 28042 | H3330: Gestion envíos locales, nacionales e internacionales | I3330: Centro de Carga Aérea Calle India 6 Parcela 1.4.b Nave 3, Madrid | J3330: 40.452462 | K3330: -3.5743393
B3331: Nacex | C3331: Estación logistica de ultima milla | D3331: Private | E3331: Industrial estate | F3331: Madrid | G3331: 28823 | H3331: Centro de distribución urbana o estación de última milla | I3331: Pol. Ind. Coslada, Av. de Fuentemar, 8 - 12, Coslada | J3331: 40.431553 | K3331: -3.5510899
B3332: SEUR | C3332: Estación logistica de ultima milla | D3332: Private | E3332: Industrial estate | F3332: Madrid | G3332: 28823 | H3332: Centro de distribución urbana o estación de última milla | I3332: Av. de Fuentemar, 21, 28823 Coslada, | J3332: 40.43437 | K3332: -3.5519219
B3333: SEUR | C3333: Centros de distribución/recepción | D3333: Private | E3333: Industrial estate | F3333: Madrid | G3333: 28021 | H3333: Centro de distribución de paquetería | I3333: Ctra. Villaverde a Vallecas, 257, Vallecas | J3333: 40.370549 | K3333: -3.6446332
B3334: SEUR | C3334: Centros de distribución/recepción | D3334: Private | E3334: Industrial estate | F3334: Madrid | G3334: 28830 | H3334: Centro de distribución urbana o estación de última milla | I3334: C. del Mar Egeo, 1, 28830 San Fernando de Henares | J3334: 40.45674 | K3334: -3.500451
B3335: SEUR | C3335: Almacén/E-fulfilment | D3335: Private | E3335: Industrial estate | F3335: Madrid | G3335: 28906 | H3335: Centro de distribución urbana o estación de última milla | I3335: C. Diseño, 2, Poligono Industrial los Olivos, Getafe | J3335: 40.31412 | K3335: -3.6833939
B3336: SEUR | C3336: Estación logistica de ultima milla | D3336: Private | E3336: Industrial estate | F3336: Madrid | G3336: 28821 | I3336: Av. de Suiza, 18-15, Coslada | J3336: 40.441207 | K3336: -3.5501772
B3337: Cainiao (AliExpress) | C3337: Centros de distribución/recepción | D3337: Private | E3337: Industrial estate | F3337: Madrid | G3337: 28830 | H3337: Hub de clasificación y distribución de Cainiao | I3337: Rda. de Marcos Ana, 6, 28830 Madrid | J3337: 40.438622 | K3337: -3.496911
B3338: Cainiao (AliExpress) | C3338: Almacén/E-fulfilment | D3338: Private | E3338: Industrial estate | F3338: Madrid | G3338: 28906 | H3338: Operaciones de última milla | I3338: C. Marconi, 24, 28906 Getafe, Madrid | J3338: 40.303176 | K3338: -3.6973099
B3339: Fedex | C3339: Centros de distribución/recepción | D3339: Private | E3339: Industrial estate | F3339: Madrid | G3339: 28042 | H3339: Recogida y agrupacion de paquetes (tráfico aéreo o intermodal) | I3339: Centro de Carga Aerea, Av. Central, 35, Barajas, 28042 Madrid | J3339: 40.453377 | K3339: -3.5715855
B3340: Fedex | C3340: Centros de distribución/recepción | D3340: Private | E3340: Industrial estate | F3340: Madrid | G3340: 28830 | H3340: Centro de distribución urbana o estación de última milla | I3340: C. Albañiles, 4, 6-8, 28830 San Fernando de Henares, Madrid | J3340: 40.444418 | K3340: -3.5057712
...

Sheet Sheet1
A1: Company | B1: Type | C1: Infrastructure | D1: Type Infrastructure | E1: City | F1: Zip Code | G1: Location | H1: Address | I1: Latitude | J1: Longitude | N1: Type | O1: Count of Infrastructure
A2: InPost | B2: Lockers | C2: Private | D2: Supermarket | E2: Madrid | F2: 28001 | G2: Supermercado Dia | H2: Calle de Nuñez de Balboa, 32 | I2: 40.425934 | J2: -3.6820859 | N2: Click&Collect | O2: 155
A3: InPost | B3: Lockers | C3: Private | D3: Parking | E3: Madrid | F3: 28001 | G3: 24/7 Parking Ayala Grupo | H3: Cl. de Ayala, 38 | I3: 40.427876 | J3: -3.6845761 | N3: Convenience stores | O3: 2207
A4: InPost | B4: Convenience stores | C4: Private | D4: Premises | E4: Madrid | F4: 28001 | G4: Grupo Hicorsa Artes Graficas | H4: Calle de Goya, 43 | I4: 40.425425 | J4: -3.6829045 | N4: Lockers | O4: 693
A5: InPost | B5: Convenience stores | C5: Private | D5: Premises | E5: Madrid | F5: 28001 | G5: Panaderia Alimentacion Lagasca | H5: Calle de Lagasca, 6 | I5: 40.421287 | J5: -3.6855704 | N5: LSP PUDOs | O5: 196
A6: InPost | B6: Convenience stores | C6: Private | D6: Premises | E6: Madrid | F6: 28001 | G6: Jesus Rodriguez Cuadros | H6: C. de Alcalá, 99 | I6: 40.421684 | J6: -3.683567 | N6: (en blanco) | O6: 1
A7: InPost | B7: Convenience stores | C7: Private | D7: Premises | E7: Madrid | F7: 28001 | G7: La Capital | H7: Calle del Gral. Pardiñas, 3 | I7: 40.424026 | J7: -3.6788843 | N7: Total general | O7: 3252
A8: InPost | B8: Convenience stores | C8: Private | D8: Premises | E8: Madrid | F8: 28001 | G8: Take Up | H8: Calle del Gral. Pardiñas, 31 | I8: 40.427107 | J8: -3.6787459
A9: InPost | B9: Lockers | C9: Public | D9: Parking | E9: Madrid | F9: 28001 | G9: 24/7 Emt Parking Recoletos | H9: P.º de Recoletos, 4 | I9: 40.420739 | J9: -3.6918522
A10: InPost | B10: Lockers | C10: Private | D10: Supermarket | E10: Madrid | F10: 28002 | G10: Locker Eroski City Sanchez Pach | H10: C. de Sánchez Pacheco | I10: 40.447746 | J10: -3.6723477
A11: InPost | B11: Convenience stores | C11: Private | D11: Premises | E11: Madrid | F11: 28002 | G11: Moran Opticos | H11: C. de López de Hoyos, 128 | I11: 40.445154 | J11: -3.6734021
A12: InPost | B12: Convenience stores | C12: Private | D12: Premises | E12: Madrid | F12: 28002 | G12: Herbolario Sana Sana | H12: C. de Pradillo, 7 | I12: 40.44896 | J12: -3.6754966
A13: InPost | B13: Convenience stores | C13: Private | D13: Premises | E13: Madrid | F13: 28002 | G13: Locutorio Robert Multiservices | H13: C. de Vinaroz, 2 | I13: 40.444972 | J13: -3.6750507
A14: InPost | B14: Convenience stores | C14: Private | D14: Premises | E14: Madrid | F14: 28002 | G14: Optica Golf | H14: C. del Príncipe de Vergara 2 | I14: 40.441907 | J14: -3.6785344
A15: InPost | B15: Lockers | C15: Private | D15: Supermarket | E15: Madrid | F15: 28002 | G15: Supermercado Dia | H15: C. de Eugenio Salazar, 27 | I15: 40.446448 | J15: -3.6748581
A16: InPost | B16: Convenience stores | C16: Private | D16: Premises | E16: Madrid | F16: 28002 | G16: Mioptico Lopez De Hoyos | H16: C. de López de Hoyos, 135 | I16: 40.447289 | J16: -3.6697828
A17: InPost | B17: Convenience stores | C17: Private | D17: Premises | E17: Madrid | F17: 28002 | G17: Digital Y Envios | H17: C/ de Baeza, 4 | I17: 40.445614 | J17: -3.6692721
A18: InPost | B18: Convenience stores | C18: Private | D18: Premises | E18: Madrid | F18: 28002 | G18: Luisipo | H18: C. de Clara del Rey, 2 | I18: 40.440245 | J18: -3.6735521
A19: InPost | B19: Lockers | C19: Private | D19: Parking | E19: Madrid | F19: 28002 | G19: Parking Clara Del Rey | H19: C. de Clara del Rey, 32 | I19: 40.443403 | J19: -3.6687157
... A26: InPost | B26: Convenience stores | C26: Private | D26: Premises | E26: Madrid | F26: 28003 | G26: La Tienda De Almudena | H26: Calle de Zurbano, 93 | I26: 40.44094 | J26: -3.6927401
A27: InPost | B27: Convenience stores | C27: Private | D27: Premises | E27: Madrid | F27: 28003 | G27: Mis Miss | H27: C. de Alonso Cano, 91 | I27: 40.444357 | J27: -3.6973242
A28: InPost | B28: Convenience stores | C28: Private | D28: Premises | E28: Madrid | F28: 28003 | G28: Baez Locutorio | H28: C. de Espronceda, 9 | I28: 40.441101 | J28: -3.698141
A29: InPost | B29: Convenience stores | C29: Private | D29: Premises | E29: Madrid | F29: 28003 | G29: Barullo Company | H29: Calle de Sta Engracia, 131 | I29: 40.442444 | J29: -3.702151
A30: InPost | B30: Convenience stores | C30: Private | D30: Premises | E30: Madrid | F30: 28003 | G30: Expendeduria 791 | H30: C/ de Ponzano, 25 | I30: 40.439226 | J30: -3.699629
A31: InPost | B31: Lockers | C31: Private | D31: Parking | E31: Madrid | F31: 28003 | G31: Locker 24/7 Parking Empark Ponz | H31: C. de Alenza, 18 | I31: 40.444416 | J31: -3.7004759
A32: InPost | B32: Lockers | C32: Private | D32: Premises | E32: Madrid | F32: 28003 | G32: Money Exchang | H32: C. de Raimundo Fernández Villaverde, 13 | I32: 40.447222 | J32: -3.7021532
A33: InPost | B33: Convenience stores | C33: Private | D33: Premises | E33: Madrid | F33: 28003 | G33: Bicicletas Y Calzado | H33: Av. de la Reina Victoria, 51 | I33: 40.446443 | J33: -3.7120553
A34: InPost | B34: Convenience stores | C34: Private | D34: Premises | E34: Madrid | F34: 28004 | G34: Nails Nactory Santa Barbara | H34: C. de Sta. Bárbara, 7 | I34: 40.424252 | J34: -3.7012663
A35: InPost | B35: Convenience stores | C35: Private | D35: Premises | E35: Madrid | F35: 28004 | G35: El Jardin De Churruca | H35: C. de Churruca, 19 | I35: 40.428212 | J35: -3.701358
A36: InPost | B36: Convenience stores | C36: Private | D36: Premises | E36: Madrid | F36: 28004 | G36: Dirtypop | H36: C. de Gravina, 1 | I36: 40.423612 | J36: -3.6985475
A37: InPost | B37: Convenience stores | C37: Private | D37: Premises | E37: Madrid | F37: 28004 | G37: Fotocopias Javipar | H37: C. de Loreto y Chicote, 13 | I37: 40.421742 | J37: -3.7044434
A38: InPost | B38: Convenience stores | C38: Private | D38: Premises | E38: Madrid | F38: 28004 | G38: Ixion Man | H38: C. de Pelayo, 9 | I38: 40.422519 | J38: -3.6991006
A39: InPost | B39: Convenience stores | C39: Private | D39: Premises | E39: Madrid | F39: 28004 | G39: El Jardin De Kika | H39: C. del Pez, 12 | I39: 40.423535 | J39: -3.7047451
A40: InPost | B40: Convenience stores | C40: Private | D40: Premises | E40: Madrid | F40: 28004 | G40: Copypez 12 | H40: C. del Pez, 12 | I40: 40.423629 | J40: -3.7048692
A41: InPost | B41: Lockers | C41: Private | D41: Parking | E41: Madrid | F41: 28004 | G41: 24/7 Parking Apk2 Plaza | H41: Plaza del Rey s/n | I41: 40.420326 | J41: -3.6961696
A42: InPost | B42: Convenience stores | C42: Private | D42: Premises | E42: Madrid | F42: 28004 | G42: The Mad Plug | H42: C. de Valverde, 35 | I42: 40.423223 | J42: -3.7018485
A43: InPost | B43: Convenience stores | C43: Private | D43: Premises | E43: Madrid | F43: 28004 | G43: Pcservice | H43: Cl. del Marqués de Sta. Ana | I43: 40.424638 | J43: -3.7049473
A44: InPost | B44: Lockers | C44: Private | D44: Premises | E44: Madrid | F44: 28004 | G44: Money Exchange Fuencarral | H44: Calle de Fuencarral & C. de las Infantas | I44: 40.421388 | J44: -3.7012384
A45: InPost | B45: Convenience stores | C45: Private | D45: Parking | E45: Madrid | F45: 28005 | G45: Locker Parking Latina | H45: C. de Toledo, 88 | I45: 40.408826 | J45: -3.7109194
A46: InPost | B46: Convenience stores | C46: Private | D46: Premises | E46: Madrid | F46: 28005 | G46: Golochuches | H46: C. de Melilla, 39 | I46: 40.400647 | J46: -3.7103177
A47: InPost | B47: Convenience stores | C47: Private | D47: Premises | E47: Madrid | F47: 28005 | G47: Estanco Piramides | H47: P.º de las Acacias, 69 | I47: 40.401131 | J47: -3.7132209
A48: InPost | B48: Convenience stores | C48: Private | D48: Premises | E48: Madrid | F48: 28005 | G48: Nuvole Di Profumo Mercado De La | H48: Pl. de la Cebada, S/N | I48: 40.41121 | J48: -3.7099362
A49: InPost | B49: Convenience stores | C49: Private | D49: Premises | E49: Madrid | F49: 28005 | G49: Optica Piramides | H49: P.º de Juan Antonio Vallejo-Nájera Botas | I49: 40.402114 | J49: -3.7080329
A50: InPost | B50: Convenience stores | C50: Private | D50: Premises | E50: Madrid | F50: 28005 | G50: Mioptico Embajadores | H50: C. de Martín de Vargas, 2 | I50: 40.404721 | J50: -3.703328
A51: InPost | B51: Lockers | C51: Private | D51: Parking | E51: Madrid | F51: 28005 | G51: Locker 24/7 Grupo Bolton Garage | H51: C/ de la Ribera de Curtidores | I51: 40.407122 | J51: -3.7073202
A52: InPost | B52: Convenience stores | C52: Private | D52: Premises | E52: Madrid | F52: 28005 | G52: Estanco 149 Pasillo Verde | H52: Pasillo Verde, P.º de Juan Antonio Vallejo-Nájera Botas, 50 | I52: 40.405026 | J52: -3.7148186
A53: InPost | B53: Lockers | C53: Public | D53: Parking | E53: Madrid | F53: 28005 | G53: Locker 24/7 Emt Mad Parking San | H53: C. San Epifanio, 9 | I53: 40.40104 | J53: -3.7192906
... A170: InPost | B170: Convenience stores | C170: Private | D170: Premises | E170: Madrid | F170: 28017 | G170: Papeleria Minfi | H170: C. de Emilio Ferrari, 88 | I170: 40.429025 | J170: -3.6395183
A171: InPost | C171: Private | D171: Premises | E171: Madrid | F171: 28017 | G171: Locutorio Y Transporte Orion | H171: C. de Mª Teresa Sáenz de Heredia, 7 | I171: 40.422532 | J171: -3.6546342
A172: InPost | B172: Convenience stores | C172: Private | D172: Premises | E172: Madrid | F172: 28017 | G172: Papeleria Adelfa | H172: C. del Poeta Blas de Otero, 32 | I172: 40.42165 | J172: -3.6517336
A173: InPost | B173: Convenience stores | C173: Private | D173: Premises | E173: Madrid | F173: 28017 | G173: Papeleria Libreria Gonzalo | H173: C/ de José Arcones Gil, 84 | I173: 40.430429 | J173: -3.6359295
A174: InPost | B174: Convenience stores | C174: Private | D174: Premises | E174: Madrid | F174: 28017 | G174: Peluqueria Y Estetica Vilans | H174: Av. de Daroca, 56 | I174: 40.429575 | J174: -3.6536036
A175: InPost | B175: Convenience stores | C175: Private | D175: Premises | E175: Madrid | F175: 28017 | G175: Locutorio El Grande | H175: C. del Río Ulla, 3 | I175: 40.435261 | J175: -3.6428924
A176: InPost | B176: Convenience stores | C176: Private | D176: Premises | E176: Madrid | F176: 28017 | G176: Electric Family | H176: C. de Vital Aza, 48 | I176: 40.432407 | J176: -3.640753
A177: InPost | B177: Convenience stores | C177: Private | D177: Premises | E177: Madrid | F177: 28017 | G177: Foto Rossny | H177: C. de Ricardo Ortiz, 8 | I177: 40.429897 | J177: -3.6582026
A178: InPost | B178: Convenience stores | C178: Private | D178: Premises | E178: Madrid | F178: 28017 | G178: Locutorio Wilson | H178: C. de Vicente Espinel, 3 | I178: 40.436217 | J178: -3.6410559
A179: InPost | B179: Convenience stores | C179: Private | D179: Premises | E179: Madrid | F179: 28017 | G179: Estanco Alcala 234 | H179: C. de Alcalá, 234 | I179: 40.431857 | J179: -3.6573869
A180: InPost | B180: Convenience stores | C180: Private | D180: Premises | E180: Madrid | F180: 28017 | G180: Tribuna Libros | H180: Calle de Portugalete, 17 | I180: 40.427056 | J180: -3.634875
A181: InPost | B181: Convenience stores | C181: Private | D181: Premises | E181: Madrid | F181: 28017 | G181: Bosco Shop | H181: C. de Ricardo Ortiz, 22 | I181: 40.42831 | J181: -3.658208
A182: InPost | B182: Convenience stores | C182: Private | D182: Premises | E182: Madrid | F182: 28017 | G182: Frada Fruit | H182: C. Paredes de Nava, 19 | I182: 40.420325 | J182: -3.6273396
A183: InPost | B183: Convenience stores | C183: Private | D183: Premises | E183: Madrid | F183: 28018 | G183: Cpumania | H183: C. del Arroyo del Olivar, 97 | I183: 40.388502 | J183: -3.6491171
... A3253: MRW | B3253: LSP PUDOs | C3253: Private | D3253: Premises | E3253: Madrid | F3253: 28042 | G3253: Oficina Mrw 02647 | H3253: Avenida Central, 18, 28042 | I3253: 40.451365 | J3253: -3.5740065

Sheet City ​​of Valencia
B2: Company | C2: Type | D2: Infrastructure | E2: Type Infrastructure | F2: City | G2: Zip Code | H2: Location | I2: Address | J2: Latitude | K2: Longitude
B4: InPost | C4: Convenience stores | D4: Private | E4: Premises | F4: Valencia | G4: 46001 | H4: Perfumarte Maria Cristina | I4: C. de María Cristina, 9 | J4: 39,47310955975495 | K4: -0.377633211837713
B5: InPost | C5: Lockers | D5: Private | E5: Premises | F5: Valencia | G5: 46003 | H5: Carmen Laundry | I5: C. de Alejandra Soler, 9 | J5: 39,47756090944269 | K5: -0.3828099665562772
B6: InPost | C6: Convenience stores | D6: Private | E6: Premises | F6: Valencia | G6: 46001 | H6: Valira Tienda De Fabrica | I6: Calle del Músico Peydró, 30 | J6: 39.47179659723847 | K6: -0.37849382111226193
B7: InPost | C7: Convenience stores | D7: Private | E7: Premises | F7: Valencia | G7: 46003 | H7: Economy Print | I7: C/ de Ripalda, 20 | J7: 39.47889580112418 | K7: -0.38124623090782084
B8: InPost | C8: Lockers | D8: Private | E8: Premises | F8: Valencia | G8: 46008 | H8: Carmen Laundry 2 | I8: C. de Quart, 125 | J8: 39.47473011396571 | K8: -0.3901642470217949
B9: InPost | C9: Lockers | D9: Private | E9: Supermarket | F9: Valencia | G9: 46008 | H9: Dia C/ Juan Llorens | I9: C. de Juan Llorens, 10 | J9: 39.47356343765982 | K9: -0.3913135158114307
B10: InPost | C10: Lockers | D10: Private | E10: Supermarket | F10: Valencia | G10: 46003 | H10: Superm Charter C/Salvado | I10: C/ de Salvador Giner, 22 | J10: 39.48075067455666 | K10: -0.3798377191040145
B11: InPost | C11: Convenience stores | D11: Private | E11: Kiosk | F11: Valencia | G11: 46008 | H11: El Quiosc | I11: C. de San Ignacio de Loyola | J11: 39.47389899460428 | K11: -0.3896573891830816
B12: InPost | C12: Convenience stores | D12: Private | E12: Premises | F12: Valencia | G12: 46008 | H12: Expendeduria 156 | I12: C. de Calixto III, 1 | J12: 39.47253854767568 | K12: -0.3867316660609
B13: InPost | C13: Convenience stores | D13: Private | E13: Premises | F13: Valencia | G13: 46008 | H13: Kalinopa | I13: Gran Vía de Fernando el Católico, 56 | J13: 39.473999706363465 | K13: -0.3868670342211692
B14: InPost | C14: Convenience stores | D14: Private | E14: Premises | F14: Valencia | G14: 46008 | H14: Outlet Destino 8 | I14: C/ Angel Guimera, 30 | J14: 39.470344474685916 | K14: -0.38684924402987636
B15: InPost | C15: Lockers | D15: Private | E15: Premises | F15: Valencia | G15: 46003 | H15: Lacolada Ciutat Vella | I15: C. de la Blanqueria, 9 | J15: 39.48015886194766 | K15: -0.377359092388655
... B98: InPost | C98: Convenience stores | D98: Private | E98: Premises | F98: Valencia | G98: 46004 | H98: Locutorio Paris | I98: C. de Luis Oliag, 40 | J98: 39.46101263079718 | K98: -0.36480913017180744
B99: InPost | C99: Lockers | D99: Private | E99: Parking | F99: Valencia | G99: 46021 | H99: 24/7 Parking Apk2 Aragon | I99: Carrer de Xile, s/n | J99: 39.47178653962879 | K99: -0.35637027
B100: InPost | C100: Lockers | D100: Private | E100: Premises | F100: Valencia | G100: 46010 | H100: Blue Onyx Lavanderia | I100: C. de Menéndez y Pelayo, 24 | J100: 39.47846682104921 | K100: -0.3554090241374535
B101: InPost | C101: Convenience stores | D101: Private | E101: Premises | F101: Valencia | G101: 46004 | H101: Js Moviles | I101: Av. Dr. Waksman, 25 | J101: 39.45662198521995 | K101: -0.37259195129060435
B102: Correos | C102: Lockers | D102: Public | E102: Public facility | F102: Valencia | G102: 46009 | H102: Correos Valencia Suc 5. La SaãDia | I102: Av. de la Constitución, 111 | J102: 39.49035630671944 | K102: -0.375452129865151
B103: Correos | C103: Lockers | D103: Private | E103: Supermarket | F103: Valencia | G103: 46008 | H103: Supermercados Consum | I103: C/ Angel Guimera, 70 | J103: 39.46979785891765 | K103: -0.39097114116827675
B104: Correos | C104: Lockers | D104: Private | E104: Supermarket | F104: Valencia | G104: 46021 | H104: Supermercados Consum | I104: Av. del Puerto, 79 | J104: 39.466254800295886 | K104: -0.35248173362930457
B105: Correos | C105: Lockers | D105: Private | E105: Supermarket | F105: Valencia | G105: 46006 | H105: Supermercados Consum | I105: C. de Sueca, 34 | J105: 39.46141306231918 | K105: -0.3750785067165566
B106: Correos | C106: Lockers | D106: Private | E106: Supermarket | F106: Valencia | G106: 46010 | H106: Supermercados Consum | I106: C. Alboraya, 31 | J106: 39.48285278565497 | K106: -0.3704926740639288
B107: Correos | C107: LSP PUDOs | D107: Public | E107: Public facility | F107: Valencia | G107: 46021 | H107: Correos Valencia Suc 13. Algirã’s | I107: C. del Poeta Mas y Ros, 20 | J107: 39.47105061897009 | K107: -0.3497979010943048
B108: Correos | C108: LSP PUDOs | D108: Public | E108: Public facility | F108: Valencia | G108: 46011 | H108: Correos Valencia Suc 6. Puerto | I108: C. Dr. Juan José Dómine, 13 | J108: 39.46221975511138 | K108: -0.3314543872585992
B109: Correos | C109: Lockers | D109: Public | E109: Public facility | F109: Valencia | G109: 46021 | H109: Correos Valencia Suc 13. Algirã’s | I109: C. del Poeta Mas y Ros, 20 | J109: 39.47105061897009 | K109: -0.3497979010943048
B110: Correos | C110: Lockers | D110: Public | E110: Public facility | F110: Valencia | G110: 46011 | H110: Correos Valencia Suc 6. Puerto | I110: C. Dr. Juan José Dómine, 13 | J110: 39.46221975511138 | K110: -0.3314543872585992
B111: Correos | C111: Lockers | D111: Public | E111: Public Infrastructure | F111: Valencia | G111: 46004 | H111: Estacion De Metro Xativa | I111: C. Xátiva, s/n | J111: 39.46761031087426 | K111: -0.3768970377143659
... B150: Amazon | C150: Convenience stores | D150: Private | E150: Premises | F150: Valencia | G150: 46005 | H150: Estanco Joaquin Costa 44 | I150: C. Joaquín Costa, 44 | J150: 39.46457344018159 | K150: -0.36625796047850223
B151: Amazon | C151: Convenience stores | D151: Private | E151: Premises | F151: Valencia | G151: 46005 | H151: Nickname Store | I151: C. de Joaquín Costa, 37 | J151: 40.44461476129101 | K151: -0.36844483
B152: Amazon | C152: Lockers | D152: Public | E152: Public facility | F152: Valencia | G152: 46005 | H152: Citypaq Lockerss-Correos València Suc 9. Joaquin Co | I152: C. de Joaquín Costa, 39 | J152: 40.44436179791772 | K152: -0.36839315
B153: Amazon | C153: Convenience stores | D153: Public | E153: Public facility | F153: Valencia | G153: 46005 | H153: Correos - València Suc 9. Joaquin Costa | I153: C. de Joaquín Costa, 39 | J153: 40.44436179791772 | K153: -0.36839315
B154: Amazon | C154: Convenience stores | D154: Private | E154: Kiosk | F154: Valencia | G154: 46005 | H154: Kiosko Angeles | I154: C. del Pintor Salvador Abril, 18 | J154: 39.463754935917095 | K154: -0.3707043261626431
B155: Amazon | C155: Convenience stores | D155: Private | E155: Premises | F155: Valencia | G155: 46005 | H155: Seur - Karpet Papeleria Tecnica | I155: C. Joaquín Costa, 46 | J155: 39.46445347966288 | K155: -0.36608867443925336
B156: Amazon | C156: Convenience stores | D156: Private | E156: Premises | F156: Valencia | G156: 46005 | H156: Seur - Texto Graf | I156: Calle de Matías Perelló, 27 | J156: 39.461753537073136 | K156: -0.3676080029272786
B157: Amazon | C157: Convenience stores | D157: Private | E157: Premises | F157: Valencia | G157: 46005 | H157: Libreria Salamanca | I157: C. de Salamanca, 42 | J157: 39.465088498072824 | K157: -0.3634071446984216
B158: Amazon | C158: Convenience stores | D158: Private | E158: Premises | F158: Valencia | G158: 46005 | H158: Papelería Barco De Papel | I158: C. de Salamanca, 47 | J158: 39.46475085560623 | K158: -0.36267141867309804
B159: Amazon | C159: Convenience stores | D159: Private | E159: Premises | F159: Valencia | G159: 46006 | H159: Estanco Garna | I159: C. de Luis Oliag, 25 | J159: 39.45959149555638 | K159: -0.36684328045319314
B160: Amazon | C160: Convenience stores | D160: Private | E160: Premises | F160: Valencia | G160: 46006 | H160: Seur - Estanco Garna Valencia 13 | I160: C. de Luis Oliag, 25 | J160: 39.45959149555638 | K160: -0.36684328045319314
B161: Amazon | C161: Convenience stores | D161: Private | E161: Premises | F161: Valencia | G161: 46006 | H161: 1x2 Mercat Russafa | I161: C. del Consulat del Mar, 5 | J161: 39.463014162723226 | K161: -0.37127278020055776
B162: Amazon | C162: Convenience stores | D162: Private | E162: Premises | F162: Valencia | G162: 46006 | H162: Seur - Ibertinta Valencia | I162: PERIS Y VALERO 85 | J162: 39.45908593409706 | K162: -0.37195494772591703
B163: Amazon | C163: Convenience stores | D163: Public | E163: Public facility | F163: Valencia | G163: 46006 | H163: Correos - València Suc 4. Ruzafa | I163: Carrer dels Sornells, 12 | J163: 39.46124947574316 | K163: -0.3712430853111239
B164: Amazon | C164: Lockers | D164: Private | E164: Supermarket | F164: Valencia | G164: 46006 | H164: Lockers Achig | I164: Avinguda del Doctor Waksman, 31 | J164: 39.4564373341664 | K164: -0.3721672263166907
B165: Amazon | C165: Convenience stores | D165: Private | E165: Premises | F165: Valencia | G165: 46006 | H165: Global Tec | I165: Ctra. de la Fuente de San Luis, 34 | J165: 39.456621236199155 | K165: -0.3718659207881171
... B447: Seur | C447: Convenience stores | D447: Private | E447: Premises | F447: Valencia | G447: 46021 | H447: Estanco 66 | I447: Avda. de Blasco Ibáñez, 39 | J447: 39.47620140147745 | K447: -0.3532717204191384
B448: Seur | C448: LSP PUDOs | D448: Private | E448: Premises | F448: Valencia | G448: 46011 | H448: Tienda SEUR | I448: C. del Dr. Josep Juan Dómine, 7 | J448: 39.463549 | K448: -0.33290706
B449: Seur | C449: LSP PUDOs | D449: Private | E449: Premises | F449: Valencia | G449: 46023 | H449: Tienda SEUR | I449: Av. de França, 10 | J449: 39.461242 | K449: -0.35155242
B450: Seur | C450: LSP PUDOs | D450: Private | E450: Premises | F450: Valencia | G450: 46005 | H450: Tienda SEUR | I450: Carrer de Joaquín Costa, 46 | J450: 39.465597 | K450: -0.36621408
B451: Seur | C451: LSP PUDOs | D451: Private | E451: Premises | F451: Valencia | G451: 46007 | H451: Tienda SEUR | I451: C/ de Sant Vicent Màrtir, 209 | J451: 39.459113 | K451: -0.3830438
B452: Seur | C452: LSP PUDOs | D452: Private | E452: Premises | F452: Valencia | G452: 46007 | H452: Tienda SEUR | I452: Av. de Gaspar Aguilar, 25 | J452: 39.459782 | K452: -0.38872239
B453: Seur | C453: LSP PUDOs | D453: Private | E453: Premises | F453: Valencia | G453: 46014 | H453: Centro Logístico SEUR | I453: C/ de l'Arxiduc Carles, 109 | J453: 39.463235 | K453: -0.39953532
B454: Seur | C454: LSP PUDOs | D454: Private | E454: Premises | F454: Valencia | G454: 46005 | H454: Tienda SEUR | I454: Gran Via del Marqués del Túria, 54 | J454: 39.468478 | K454: -0.3685149
B455: Seur | C455: LSP PUDOs | D455: Private | E455: Premises | F455: Valencia | G455: 46022 | H455: Tienda SEUR | I455: C/ dels Sants Just i Pastor, 80 | J455: 39.470156 | K455: -0.34618026
B456: Seur | C456: LSP PUDOs | D456: Private | E456: Premises | F456: Valencia | G456: 46018 | H456: Tienda SEUR | I456: Brasil, 12 | J456: 39.472566 | K456: -0.3967371
B457: Seur | C457: LSP PUDOs | D457: Private | E457: Premises | F457: Valencia | G457: 46015 | H457: Tienda SEUR | I457: C/ de Miguel Servet, 11 | J457: 39.489729 | K457: -0.39382939
B458: Seur | C458: LSP PUDOs | D458: Private | E458: Premises | F458: Valencia | G458: 46025 | H458: SEUR Pickup parcelshop | I458: Av. de Joan XXIII, 4 | J458: 39.493165 | K458: -0.38260657
B459: Seur | C459: LSP PUDOs | D459: Private | E459: Premises | F459: Valencia | G459: 46019 | H459: Tienda SEUR | I459: C/ de St. Joan de la Penya, 32 | J459: 39.497172 | K459: -0.36795111
B460: Seur | C460: LSP PUDOs | D460: Private | E460: Premises | F460: Valencia | G460: 46011 | H460: Tienda SEUR | I460: Av.de la Malva-Rosa, 35 | J460: 39.479669 | K460: -0.32939843
B461: DHL | C461: Convenience stores | D461: Private | E461: Premises | F461: Valecia | G461: 46008 | H461: Candy 46007 | I461: Gran Vía de Fernando el Católico, 34 | J461: 39.47249257289682 | K461: -0.3859082290873535
B462: DHL | C462: Convenience stores | D462: Private | E462: Premises | F462: Valecia | G462: 46003 | H462: Naturalworld | I462: Pl. de los Fueros, 1 | J462: 39.479155490406676 | K462: -0.3763804351401032
B463: DHL | C463: Convenience stores | D463: Private | E463: Premises | F463: Valecia | G463: 46008 | H463: Granujas Valencia | I463: C. de Calixto III, 18 | J463: 39.47153989776263 | K463: -0.38941329980675043
B464: DHL | C464: Convenience stores | D464: Private | E464: Premises | F464: Valecia | G464: 46007 | H464: Informatica Ecoturia | I464: C. Alcira, 4 | J464: 39.467395252359736 | K464: -0.38518203370248894
B465: DHL | C465: LSP PUDOs | D465: Private | E465: Premises | F465: Valecia | G465: 46004 | H465: Dhl Express Center Valencia | I465: Cl. de Colón, 43 | J465: 39.4713992063019 | K465: -0.36963931959088814
B466: DHL | C466: Convenience stores | D466: Private | E466: Premises | F466: Valecia | G466: 46009 | H466: Alonso Salinas | I466: Av. de la Constitución, 9 | J466: 39.484045898060806 | K466: -0.3790060857165573
B467: DHL | C467: Convenience stores | D467: Private | E467: Premises | F467: Valecia | G467: 46006 | H467: Mascletá Bike Rental | I467: C. de Cuba, 1 | J467: 39.463010368404746 | K467: -0.3776497535013315
B468: DHL | C468: Convenience stores | D468: Private | E468: Premises | F468: Valecia | G468: 46018 | H468: Estanco 61 Valencia | I468: Av. de Burjassot, 35 | J468: 39.48526488673293 | K468: -0.3855126595941645
B469: DHL | C469: Convenience stores | D469: Private | E469: Kiosk | F469: Valecia | G469: 46018 | H469: Kiosko Papeleria Totana | I469: C. Totana, 1 | J469: 39.46952496526851 | K469: -0.3946429952320456
B470: DHL | C470: Convenience stores | D470: Private | E470: Premises | F470: Valecia | G470: 46018 | H470: Carlin El Cid | I470: Av. del Cid, 48 | J470: 39.468643854761005 | K470: -0.3967504664930497
B471: DHL | C471: Convenience stores | D471: Private | E471: Premises | F471: Valecia | G471: 46010 | H471: Planta Loca | I471: C. Alboraya, 45 | J471: 39.4847093995961 | K471: -0.36944178567814767
B472: DHL | C472: Convenience stores | D472: Private | E472: Premises | F472: Valecia | G472: 46015 | H472: Loterias Marcos Fotografia Mas | I472: C/ de la Vall de la Ballestera, 36 | J472: 39.47950491502379 | K472: -0.3981345548622465
... B501: DHL | C501: Convenience stores | D501: Private | E501: Premises | F501: Valecia | G501: 46026 | H501: La Bruixa De Castellar | I501: C. José Siurana, 4 | J501: 39.42930910360358 | K501: -0.36324773281640477
B502: DHL | C502: Convenience stores | D502: Private | E502: Premises | F502: Valecia | G502: 46011 | H502: Punto de Venta DHL Express (FOLDER REINA VALENCIA) | I502: C/ de la Reina, 7, Poblats Marítims | J502: 39.466619 | K502: -0.32926406
B503: DHL | C503: Convenience stores | D503: Private | E503: Premises | F503: Valecia | G503: 46023 | H503: Punto de Venta DHL Express (FIX VALENCIA) | I503: Carrer de Higinio Noja (Professor), 61, Camins al Grau | J503: 39.461066 | K503: -0.34849356
B504: DHL | C504: Convenience stores | D504: Private | E504: Premises | F504: Valecia | G504: 46022 | H504: Punto de Venta DHL Express (THE PHONE SHOP) | I504: Av. del Port, 121, Camins al Grau | J504: 39.467282 | K504: -0.3481027
B505: DHL | C505: Convenience stores | D505: Private | E505: Premises | F505: Valecia | G505: 46005 | H505: Punto de Venta DHL Express (PCBOX) | I505: Carrer de Salamanca, 48 | J505: 39.466649 | K505: -0.36268325
B506: DHL | C506: Convenience stores | D506: Private | E506: Premises | F506: Valecia | G506: 46004 | H506: Punto de Venta DHL Express (OHFFICE RUZAFA) | I506: C/ de Russafa, 22 | J506: 39.467451 | K506: -0.37470037
B507: DHL | C507: LSP PUDOs | D507: Private | E507: Premises | F507: Valecia | G507: 46007 | H507: Punto de Servicio DHL EXPRESS | I507: C/ d'Alzira, 4 | J507: 39.468769 | K507: -0.38478535
B508: DHL | C508: Convenience stores | D508: Private | E508: Premises | F508: Valecia | G508: 46007 | H508: Punto de Venta DHL Express (PCBOX) | I508: Gran Vía de Ramón y Cajal, 49 | J508: 39.470756 | K508: -0.38375313
B509: DHL | C509: LSP PUDOs | D509: Private | E509: Premises | F509: Valecia | G509: 46004 | H509: DHL Express Service Point | I509: Carrer de Colón, 37 | J509: 39.473026 | K509: -0.37003274
B510: DHL | C510: Convenience stores | D510: Private | E510: Premises | F510: Valecia | G510: 46014 | H510: Punto de Venta DHL Express (QHR) | I510: Plaça de l'Alqueria Nova, 1 | J510: 39.472586 | K510: -0.41847271
B511: DHL | C511: Convenience stores | D511: Private | E511: Premises | F511: Valecia | G511: 46021 | H511: Punto de Venta DHL Express (MUPIPRINT) | I511: Av. de Blasco Ibáñez, 72, Bajo Izqda | J511: 39.478085 | K511: -0.35238758
B512: DHL | C512: Convenience stores | D512: Private | E512: Premises | F512: Valecia | G512: 46010 | H512: Punto de Venta DHL Express (PCBOX) | I512: C/ de les Arts Gràfiques, 14, Bajo | J512: 39.479979 | K512: -0.36177568
B513: DHL | C513: Convenience stores | D513: Private | E513: Premises | F513: Valecia | G513: 46003 | H513: Punto de Venta DHL Express (FOLDER) | I513: C/ de la Pau, 25, Ciutat Vella | J513: 39.474887 | K513: -0.37175747
... B517: DHL | C517: Convenience stores | D517: Private | E517: Premises | F517: Valecia | G517: 46025 | H517: Punto de Venta DHL Express (VALFER EXPRESS) | I517: C/ de Vicent Canet, 7, Bajo Dcha | J517: 39.503022 | K517: -0.39223604
B518: Celeritas | C518: Convenience stores | D518: Private | E518: Premises | F518: Valecia | G518: 46004 | H518: Uala Accesorios | I518: C. de Ruzafa, 14 | J518: 39.466232012440535 | K518: -0.3743313920297572
B519: Celeritas | C519: Convenience stores | D519: Private | E519: Kiosk | F519: Valecia | G519: 46004 | H519: Kiosko De Calle La Paraeta | I519: Av. de Navarro Reverter, 5 | J519: 39.47244629205207 | K519: -0.36738764730123064
B520: Celeritas | C520: Convenience stores | D520: Private | E520: Premises | F520: Valecia | G520: 46001 | H520: Merceria Lana Negra | I520: C. de Huesca, 6 | J520: 39.46957741762155 | K520: -0.3804449349056476
B521: Celeritas | C521: Convenience stores | D521: Private | E521: Kiosk | F521: Valecia | G521: 46007 | H521: Kiosco Guillen De Castro | I521: C/ Guillem de Castro, 55 | J521: 39.470481889709696 | K521: -0.3832721019181088
B522: Celeritas | C522: Convenience stores | D522: Private | E522: Premises | F522: Valecia | G522: 46008 | H522: Bazar 28 De Septiembre | I522: C/ Guillem de Castro, 69 | J522: 39.47136589622819 | K522: -0.3839602588172939
B523: Celeritas | C523: Convenience stores | D523: Private | E523: Premises | F523: Valecia | G523: 46008 | H523: Candy | I523: Gran Vía de Fernando el Católico, 34 | J523: 39.47254225565486 | K523: -0.3859083159766075
B524: Celeritas | C524: Convenience stores | D524: Private | E524: Premises | F524: Valecia | G524: 46008 | H524: Expendeduria 156 | I524: C. de Calixto III, 1 | J524: 39.4721772951249 | K524: -0.38683104776201443
B525: Celeritas | C525: Convenience stores | D525: Private | E525: Premises | F525: Valecia | G525: 46008 | H525: Estanco Valencia 85 | I525: Av. de Pérez Galdós, 100 | J525: 39.471066370384285 | K525: -0.3925271334269611
B526: Celeritas | C526: Convenience stores | D526: Private | E526: Premises | F526: Valecia | G526: 46003 | H526: Naturalworld | I526: Pl. de los Fueros, 1 | J526: 39.47904901005767 | K526: -0.3763810218837944
B527: Celeritas | C527: Convenience stores | D527: Private | E527: Premises | F527: Valecia | G527: 46008 | H527: Joisfe | I527: C. del Historiador Sanchis Sivera, 24 | J527: 39.46874502509329 | K527: -0.38731127900024404
B528: Celeritas | C528: Convenience stores | D528: Private | E528: Premises | F528: Valecia | G528: 46005 | H528: Estanco Prensa C/ Joaquin Costa 44 | I528: C. Joaquín Costa, 44 | J528: 39.46458378558827 | K528: -0.36622210881977557
B529: Celeritas | C529: Convenience stores | D529: Private | E529: Premises | F529: Valecia | G529: 46005 | H529: Doctor Manzana | I529: Av. del Reino de Valencia, 18 | J529: 39.46447880097586 | K529: -0.3715899939196278
... B811: GLS | C811: Convenience stores | D811: Private | E811: Premises | F811: Valencia | G811: 46035 | H811: Ps Bambini Moda Infantil Y Mujer | I811: C / Campamento 44 bajo | J811: 39.50226890615729 | K811: -0.4220765706309232
B812: GLS | C812: LSP PUDOs | D812: Private | E812: Premises | F812: Valencia | G812: 46026 | H812: GLS Valencia Electrón Mensajeros, S.L. | I812: C. Juan Ramón Jiménez, 67 | J812: 39.456561 | K812: -0.37377596
B813: GLS | C813: LSP PUDOs | D813: Private | E813: Premises | F813: Valencia | G813: 46014 | H813: GLS Transporte Urgente | I813: Carrer de la Puebla de Valverde, 5 | J813: 39.464795 | K813: -0.40157617
B814: GLS | C814: LSP PUDOs | D814: Private | E814: Premises | F814: Valencia | G814: 46005 | H814: GLS | Agencia Reino de Valencia | I814: Carrer de Borriana, 14 | J814: 39.470607 | K814: -0.36554007
B815: GLS | C815: LSP PUDOs | D815: Private | E815: Premises | F815: Valencia | G815: 46005 | H815: Gestimil Valencia GLS | I815: C. de Gregori Mayans, 4 | J815: 39.469818 | K815: -0.3734367
...

Sheet Sheet3
A1: Company | B1: Type | C1: Infrastructure | D1: Type Infrastructure | E1: City | F1: Zip Code | G1: Location | H1: Address | I1: Latitude | J1: Longitude | M1: Type | N1: Count of Company
A2: InPost | B2: Convenience stores | C2: Private | D2: Premises | E2: Valencia | F2: 46001 | G2: Perfumarte Maria Cristina | H2: C. de María Cristina, 9 | I2: 39,47310955975495 | J2: -0.377633211837713 | M2: Click&Collect | N2: 24
A3: InPost | B3: Lockers | C3: Private | D3: Premises | E3: Valencia | F3: 46003 | G3: Carmen Laundry | H3: C. de Alejandra Soler, 9 | I3: 39,47756090944269 | J3: -0.3828099665562772 | M3: Convenience stores | N3: 768
A4: InPost | B4: Convenience stores | C4: Private | D4: Premises | E4: Valencia | F4: 46001 | G4: Valira Tienda De Fabrica | H4: Calle del Músico Peydró, 30 | I4: 39.47179659723847 | J4: -0.37849382111226193 | M4: Lockers | N4: 126
A5: InPost | B5: Convenience stores | C5: Private | D5: Premises | E5: Valencia | F5: 46003 | G5: Economy Print | H5: C/ de Ripalda, 20 | I5: 39.47889580112418 | J5: -0.38124623090782084 | M5: LSP PUDOs | N5: 48
A6: InPost | B6: Lockers | C6: Private | D6: Premises | E6: Valencia | F6: 46008 | G6: Carmen Laundry 2 | H6: C. de Quart, 125 | I6: 39.47473011396571 | J6: -0.3901642470217949 | M6: Total general | N6: 966
A7: InPost | B7: Lockers | C7: Private | D7: Supermarket | E7: Valencia | F7: 46008 | G7: Dia C/ Juan Llorens | H7: C. de Juan Llorens, 10 | I7: 39.47356343765982 | J7: -0.3913135158114307
A8: InPost | B8: Lockers | C8: Private | D8: Supermarket | E8: Valencia | F8: 46003 | G8: Superm Charter C/Salvado | H8: C/ de Salvador Giner, 22 | I8: 39.48075067455666 | J8: -0.3798377191040145
A9: InPost | B9: Convenience stores | C9: Private | D9: Kiosk | E9: Valencia | F9: 46008 | G9: El Quiosc | H9: C. de San Ignacio de Loyola | I9: 39.47389899460428 | J9: -0.3896573891830816
A10: InPost | B10: Convenience stores | C10: Private | D10: Premises | E10: Valencia | F10: 46008 | G10: Expendeduria 156 | H10: C. de Calixto III, 1 | I10: 39.47253854767568 | J10: -0.3867316660609
A11: InPost | B11: Convenience stores | C11: Private | D11: Premises | E11: Valencia | F11: 46008 | G11: Kalinopa | H11: Gran Vía de Fernando el Católico, 56 | I11: 39.473999706363465 | J11: -0.3868670342211692
A12: InPost | B12: Convenience stores | C12: Private | D12: Premises | E12: Valencia | F12: 46008 | G12: Outlet Destino 8 | H12: C/ Angel Guimera, 30 | I12: 39.470344474685916 | J12: -0.38684924402987636
A13: InPost | B13: Lockers | C13: Private | D13: Premises | E13: Valencia | F13: 46003 | G13: Lacolada Ciutat Vella | H13: C. de la Blanqueria, 9 | I13: 39.48015886194766 | J13: -0.377359092388655
A14: InPost | B14: Convenience stores | C14: Private | D14: Premises | E14: Valencia | F14: 46008 | G14: Milar Gran Via | H14: Gran Vía de Fernando el Católico, 3 | I14: 39.46946482690077 | J14: -0.3846478777238517
A15: InPost | B15: Convenience stores | C15: Private | D15: Premises | E15: Valencia | F15: 46003 | G15: Naturalworld | H15: Carrer de Roteros, 2 | I15: 39.47915825477076 | J15: -0.37623654083541874
A16: InPost | B16: Convenience stores | C16: Private | D16: Premises | E16: Valencia | F16: 46008 | G16: Plantas Y Flores Lantana | H16: Calle de Sta. María Micaela | I16: 39.47227140704873 | J16: -0.39205425075201217
A17: InPost | B17: Convenience stores | C17: Private | D17: Premises | E17: Valencia | F17: 46009 | G17: El Trebol Del Turia | H17: Av. de Burjassot, 18 | I17: 39.484222876226845 | J17: -0.38252617528850646
A18: InPost | B18: Convenience stores | C18: Private | D18: Premises | E18: Valencia | F18: 46008 | G18: Firdos Movil | H18: C. de Martín el Humano, 30 | I18: 39.46981902183968 | J18: -0.3902598607606746
... A95: InPost | B95: Convenience stores | C95: Private | D95: Premises | E95: Valencia | F95: 46004 | G95: Locutorio Paris | H95: C. de Luis Oliag, 40 | I95: 39.46101263079718 | J95: -0.36480913017180744
A96: InPost | B96: Lockers | C96: Private | D96: Parking | E96: Valencia | F96: 46021 | G96: 24/7 Parking Apk2 Aragon | H96: Carrer de Xile, s/n | I96: 39.47178653962879 | J96: -0.35637027
A97: InPost | B97: Lockers | C97: Private | D97: Premises | E97: Valencia | F97: 46010 | G97: Blue Onyx Lavanderia | H97: C. de Menéndez y Pelayo, 24 | I97: 39.47846682104921 | J97: -0.3554090241374535
A98: InPost | B98: Convenience stores | C98: Private | D98: Premises | E98: Valencia | F98: 46004 | G98: Js Moviles | H98: Av. Dr. Waksman, 25 | I98: 39.45662198521995 | J98: -0.37259195129060435
A99: Correos | B99: Lockers | C99: Public | D99: Public facility | E99: Valencia | F99: 46009 | G99: Correos Valencia Suc 5. La SaãDia | H99: Av. de la Constitución, 111 | I99: 39.49035630671944 | J99: -0.375452129865151
A100: Correos | B100: Lockers | C100: Private | D100: Supermarket | E100: Valencia | F100: 46008 | G100: Supermercados Consum | H100: C/ Angel Guimera, 70 | I100: 39.46979785891765 | J100: -0.39097114116827675
A101: Correos | B101: Lockers | C101: Private | D101: Supermarket | E101: Valencia | F101: 46021 | G101: Supermercados Consum | H101: Av. del Puerto, 79 | I101: 39.466254800295886 | J101: -0.35248173362930457
A102: Correos | B102: Lockers | C102: Private | D102: Supermarket | E102: Valencia | F102: 46006 | G102: Supermercados Consum | H102: C. de Sueca, 34 | I102: 39.46141306231918 | J102: -0.3750785067165566
A103: Correos | B103: Lockers | C103: Private | D103: Supermarket | E103: Valencia | F103: 46010 | G103: Supermercados Consum | H103: C. Alboraya, 31 | I103: 39.48285278565497 | J103: -0.3704926740639288
A104: Correos | B104: LSP PUDOs | C104: Public | D104: Public facility | E104: Valencia | F104: 46021 | G104: Correos Valencia Suc 13. Algirã’s | H104: C. del Poeta Mas y Ros, 20 | I104: 39.47105061897009 | J104: -0.3497979010943048
A105: Correos | B105: LSP PUDOs | C105: Public | D105: Public facility | E105: Valencia | F105: 46011 | G105: Correos Valencia Suc 6. Puerto | H105: C. Dr. Juan José Dómine, 13 | I105: 39.46221975511138 | J105: -0.3314543872585992
A106: Correos | B106: Lockers | C106: Public | D106: Public Infrastructure | E106: Valencia | F106: 46004 | G106: Estacion De Metro Xativa | H106: C. Xátiva, s/n | I106: 39.46761031087426 | J106: -0.3768970377143659
A107: Correos | B107: LSP PUDOs | C107: Public | D107: Public facility | E107: Valencia | F107: 46023 | G107: Correos Valencia Suc 22. El Corte Inglã‰S Av. Francia | H107: C/ del Pintor Maella, 37 | I107: 39.45707810033234 | J107: -0.34715042196515755
A108: Correos | B108: LSP PUDOs | C108: Public | D108: Public facility | E108: Valencia | F108: 46015 | G108: Correos Valencia Suc 10. Benicalap | H108: Av. del General Avilés, 8 | I108: 39.48837160586209 | J108: -0.3913537116204853
... A142: Amazon | B142: Convenience stores | C142: Private | D142: Premises | E142: Valencia | F142: 46005 | G142: Estanco Joaquin Costa 44 | H142: C. Joaquín Costa, 44 | I142: 39.46457344018159 | J142: -0.36625796047850223
A143: Amazon | B143: Convenience stores | C143: Private | D143: Premises | E143: Valencia | F143: 46005 | G143: Nickname Store | H143: C. de Joaquín Costa, 37 | I143: 40.44461476129101 | J143: -0.36844483
A144: Amazon | B144: Lockers | C144: Public | D144: Public facility | E144: Valencia | F144: 46005 | G144: Citypaq Lockerss-Correos València Suc 9. Joaquin Co | H144: C. de Joaquín Costa, 39 | I144: 40.44436179791772 | J144: -0.36839315
A145: Amazon | B145: Convenience stores | C145: Private | D145: Kiosk | E145: Valencia | F145: 46005 | G145: Kiosko Angeles | H145: C. del Pintor Salvador Abril, 18 | I145: 39.463754935917095 | J145: -0.3707043261626431
A146: Amazon | B146: Convenience stores | C146: Private | D146: Premises | E146: Valencia | F146: 46005 | G146: Seur - Karpet Papeleria Tecnica | H146: C. Joaquín Costa, 46 | I146: 39.46445347966288 | J146: -0.36608867443925336
A147: Amazon | B147: Convenience stores | C147: Private | D147: Premises | E147: Valencia | F147: 46005 | G147: Seur - Texto Graf | H147: Calle de Matías Perelló, 27 | I147: 39.461753537073136 | J147: -0.3676080029272786
A148: Amazon | B148: Convenience stores | C148: Private | D148: Premises | E148: Valencia | F148: 46005 | G148: Libreria Salamanca | H148: C. de Salamanca, 42 | I148: 39.465088498072824 | J148: -0.3634071446984216
A149: Amazon | B149: Convenience stores | C149: Private | D149: Premises | E149: Valencia | F149: 46005 | G149: Papelería Barco De Papel | H149: C. de Salamanca, 47 | I149: 39.46475085560623 | J149: -0.36267141867309804
A150: Amazon | B150: Convenience stores | C150: Private | D150: Premises | E150: Valencia | F150: 46006 | G150: Estanco Garna | H150: C. de Luis Oliag, 25 | I150: 39.45959149555638 | J150: -0.36684328045319314
A151: Amazon | B151: Convenience stores | C151: Private | D151: Premises | E151: Valencia | F151: 46006 | G151: 1x2 Mercat Russafa | H151: C. del Consulat del Mar, 5 | I151: 39.463014162723226 | J151: -0.37127278020055776
A152: Amazon | B152: Convenience stores | C152: Private | D152: Premises | E152: Valencia | F152: 46006 | G152: Seur - Ibertinta Valencia | H152: PERIS Y VALERO 85 | I152: 39.45908593409706 | J152: -0.37195494772591703
A153: Amazon | B153: Convenience stores | C153: Public | D153: Public facility | E153: Valencia | F153: 46006 | G153: Correos - València Suc 4. Ruzafa | H153: Carrer dels Sornells, 12 | I153: 39.46124947574316 | J153: -0.3712430853111239
A154: Amazon | B154: Lockers | C154: Private | D154: Supermarket | E154: Valencia | F154: 46006 | G154: Lockers Achig | H154: Avinguda del Doctor Waksman, 31 | I154: 39.4564373341664 | J154: -0.3721672263166907
A155: Amazon | B155: Convenience stores | C155: Private | D155: Premises | E155: Valencia | F155: 46006 | G155: Global Tec | H155: Ctra. de la Fuente de San Luis, 34 | I155: 39.456621236199155 | J155: -0.3718659207881171
A156: Amazon | B156: Convenience stores | C156: Private | D156: Premises | E156: Valencia | F156: 46006 | G156: Soluciones Móviles | H156: C. del Consulat del Mar, 5 | I156: 39.46314124081307 | J156: -0.37134365009783515
... A430: Seur | B430: Convenience stores | C430: Private | D430: Premises | E430: Valencia | F430: 46021 | G430: Estanco 66 | H430: Avda. de Blasco Ibáñez, 39 | I430: 39.47620140147745 | J430: -0.3532717204191384
A431: Seur | B431: LSP PUDOs | C431: Private | D431: Premises | E431: Valencia | F431: 46011 | G431: Tienda SEUR | H431: C. del Dr. Josep Juan Dómine, 7 | I431: 39.463549 | J431: -0.33290706
A432: Seur | B432: LSP PUDOs | C432: Private | D432: Premises | E432: Valencia | F432: 46023 | G432: Tienda SEUR | H432: Av. de França, 10 | I432: 39.461242 | J432: -0.35155242
A433: Seur | B433: LSP PUDOs | C433: Private | D433: Premises | E433: Valencia | F433: 46005 | G433: Tienda SEUR | H433: Carrer de Joaquín Costa, 46 | I433: 39.465597 | J433: -0.36621408
A434: Seur | B434: LSP PUDOs | C434: Private | D434: Premises | E434: Valencia | F434: 46007 | G434: Tienda SEUR | H434: C/ de Sant Vicent Màrtir, 209 | I434: 39.459113 | J434: -0.3830438
A435: Seur | B435: LSP PUDOs | C435: Private | D435: Premises | E435: Valencia | F435: 46007 | G435: Tienda SEUR | H435: Av. de Gaspar Aguilar, 25 | I435: 39.459782 | J435: -0.38872239
A436: Seur | B436: LSP PUDOs | C436: Private | D436: Premises | E436: Valencia | F436: 46014 | G436: Centro Logístico SEUR | H436: C/ de l'Arxiduc Carles, 109 | I436: 39.463235 | J436: -0.39953532
A437: Seur | B437: LSP PUDOs | C437: Private | D437: Premises | E437: Valencia | F437: 46005 | G437: Tienda SEUR | H437: Gran Via del Marqués del Túria, 54 | I437: 39.468478 | J437: -0.3685149
A438: Seur | B438: LSP PUDOs | C438: Private | D438: Premises | E438: Valencia | F438: 46022 | G438: Tienda SEUR | H438: C/ dels Sants Just i Pastor, 80 | I438: 39.470156 | J438: -0.34618026
A439: Seur | B439: LSP PUDOs | C439: Private | D439: Premises | E439: Valencia | F439: 46018 | G439: Tienda SEUR | H439: Brasil, 12 | I439: 39.472566 | J439: -0.3967371
A440: Seur | B440: LSP PUDOs | C440: Private | D440: Premises | E440: Valencia | F440: 46015 | G440: Tienda SEUR | H440: C/ de Miguel Servet, 11 | I440: 39.489729 | J440: -0.39382939
A441: Seur | B441: LSP PUDOs | C441: Private | D441: Premises | E441: Valencia | F441: 46025 | G441: SEUR Pickup parcelshop | H441: Av. de Joan XXIII, 4 | I441: 39.493165 | J441: -0.38260657
A442: Seur | B442: LSP PUDOs | C442: Private | D442: Premises | E442: Valencia | F442: 46019 | G442: Tienda SEUR | H442: C/ de St. Joan de la Penya, 32 | I442: 39.497172 | J442: -0.36795111
A443: Seur | B443: LSP PUDOs | C443: Private | D443: Premises | E443: Valencia | F443: 46011 | G443: Tienda SEUR | H443: Av.de la Malva-Rosa, 35 | I443: 39.479669 | J443: -0.32939843
A444: DHL | B444: Convenience stores | C444: Private | D444: Premises | E444: Valecia | F444: 46008 | G444: Candy 46007 | H444: Gran Vía de Fernando el Católico, 34 | I444: 39.47249257289682 | J444: -0.3859082290873535
A445: DHL | B445: Convenience stores | C445: Private | D445: Premises | E445: Valecia | F445: 46003 | G445: Naturalworld | H445: Pl. de los Fueros, 1 | I445: 39.479155490406676 | J445: -0.3763804351401032
A446: DHL | B446: Convenience stores | C446: Private | D446: Premises | E446: Valecia | F446: 46008 | G446: Granujas Valencia | H446: C. de Calixto III, 18 | I446: 39.47153989776263 | J446: -0.38941329980675043
A447: DHL | B447: Convenience stores | C447: Private | D447: Premises | E447: Valecia | F447: 46007 | G447: Informatica Ecoturia | H447: C. Alcira, 4 | I447: 39.467395252359736 | J447: -0.38518203370248894
A448: DHL | B448: LSP PUDOs | C448: Private | D448: Premises | E448: Valecia | F448: 46004 | G448: Dhl Express Center Valencia | H448: Cl. de Colón, 43 | I448: 39.4713992063019 | J448: -0.36963931959088814
A449: DHL | B449: Convenience stores | C449: Private | D449: Premises | E449: Valecia | F449: 46009 | G449: Alonso Salinas | H449: Av. de la Constitución, 9 | I449: 39.484045898060806 | J449: -0.3790060857165573
A450: DHL | B450: Convenience stores | C450: Private | D450: Premises | E450: Valecia | F450: 46006 | G450: Mascletá Bike Rental | H450: C. de Cuba, 1 | I450: 39.463010368404746 | J450: -0.3776497535013315
A451: DHL | B451: Convenience stores | C451: Private | D451: Premises | E451: Valecia | F451: 46018 | G451: Estanco 61 Valencia | H451: Av. de Burjassot, 35 | I451: 39.48526488673293 | J451: -0.3855126595941645
A452: DHL | B452: Convenience stores | C452: Private | D452: Kiosk | E452: Valecia | F452: 46018 | G452: Kiosko Papeleria Totana | H452: C. Totana, 1 | I452: 39.46952496526851 | J452: -0.3946429952320456
A453: DHL | B453: Convenience stores | C453: Private | D453: Premises | E453: Valecia | F453: 46018 | G453: Carlin El Cid | H453: Av. del Cid, 48 | I453: 39.468643854761005 | J453: -0.3967504664930497
A454: DHL | B454: Convenience stores | C454: Private | D454: Premises | E454: Valecia | F454: 46010 | G454: Planta Loca | H454: C. Alboraya, 45 | I454: 39.4847093995961 | J454: -0.36944178567814767
A455: DHL | B455: Convenience stores | C455: Private | D455: Premises | E455: Valecia | F455: 46015 | G455: Loterias Marcos Fotografia Mas | H455: C/ de la Vall de la Ballestera, 36 | I455: 39.47950491502379 | J455: -0.3981345548622465
... A484: DHL | B484: Convenience stores | C484: Private | D484: Premises | E484: Valecia | F484: 46026 | G484: La Bruixa De Castellar | H484: C. José Siurana, 4 | I484: 39.42930910360358 | J484: -0.36324773281640477
A485: DHL | B485: Convenience stores | C485: Private | D485: Premises | E485: Valecia | F485: 46011 | G485: Punto de Venta DHL Express (FOLDER REINA VALENCIA) | H485: C/ de la Reina, 7, Poblats Marítims | I485: 39.466619 | J485: -0.32926406
A486: DHL | B486: Convenience stores | C486: Private | D486: Premises | E486: Valecia | F486: 46023 | G486: Punto de Venta DHL Express (FIX VALENCIA) | H486: Carrer de Higinio Noja (Professor), 61, Camins al Grau | I486: 39.461066 | J486: -0.34849356
A487: DHL | B487: Convenience stores | C487: Private | D487: Premises | E487: Valecia | F487: 46022 | G487: Punto de Venta DHL Express (THE PHONE SHOP) | H487: Av. del Port, 121, Camins al Grau | I487: 39.467282 | J487: -0.3481027
A488: DHL | B488: Convenience stores | C488: Private | D488: Premises | E488: Valecia | F488: 46005 | G488: Punto de Venta DHL Express (PCBOX) | H488: Carrer de Salamanca, 48 | I488: 39.466649 | J488: -0.36268325
A489: DHL | B489: Convenience stores | C489: Private | D489: Premises | E489: Valecia | F489: 46004 | G489: Punto de Venta DHL Express (OHFFICE RUZAFA) | H489: C/ de Russafa, 22 | I489: 39.467451 | J489: -0.37470037
A490: DHL | B490: LSP PUDOs | C490: Private | D490: Premises | E490: Valecia | F490: 46007 | G490: Punto de Servicio DHL EXPRESS | H490: C/ d'Alzira, 4 | I490: 39.468769 | J490: -0.38478535
A491: DHL | B491: Convenience stores | C491: Private | D491: Premises | E491: Valecia | F491: 46007 | G491: Punto de Venta DHL Express (PCBOX) | H491: Gran Vía de Ramón y Cajal, 49 | I491: 39.470756 | J491: -0.38375313
A492: DHL | B492: LSP PUDOs | C492: Private | D492: Premises | E492: Valecia | F492: 46004 | G492: DHL Express Service Point | H492: Carrer de Colón, 37 | I492: 39.473026 | J492: -0.37003274
A493: DHL | B493: Convenience stores | C493: Private | D493: Premises | E493: Valecia | F493: 46014 | G493: Punto de Venta DHL Express (QHR) | H493: Plaça de l'Alqueria Nova, 1 | I493: 39.472586 | J493: -0.41847271
A494: DHL | B494: Convenience stores | C494: Private | D494: Premises | E494: Valecia | F494: 46021 | G494: Punto de Venta DHL Express (MUPIPRINT) | H494: Av. de Blasco Ibáñez, 72, Bajo Izqda | I494: 39.478085 | J494: -0.35238758
A495: DHL | B495: Convenience stores | C495: Private | D495: Premises | E495: Valecia | F495: 46010 | G495: Punto de Venta DHL Express (PCBOX) | H495: C/ de les Arts Gràfiques, 14, Bajo | I495: 39.479979 | J495: -0.36177568
A496: DHL | B496: Convenience stores | C496: Private | D496: Premises | E496: Valecia | F496: 46003 | G496: Punto de Venta DHL Express (FOLDER) | H496: C/ de la Pau, 25, Ciutat Vella | I496: 39.474887 | J496: -0.37175747
... A500: DHL | B500: Convenience stores | C500: Private | D500: Premises | E500: Valecia | F500: 46025 | G500: Punto de Venta DHL Express (VALFER EXPRESS) | H500: C/ de Vicent Canet, 7, Bajo Dcha | I500: 39.503022 | J500: -0.39223604
A501: Celeritas | B501: Convenience stores | C501: Private | D501: Premises | E501: Valecia | F501: 46004 | G501: Uala Accesorios | H501: C. de Ruzafa, 14 | I501: 39.466232012440535 | J501: -0.3743313920297572
A502: Celeritas | B502: Convenience stores | C502: Private | D502: Kiosk | E502: Valecia | F502: 46004 | G502: Kiosko De Calle La Paraeta | H502: Av. de Navarro Reverter, 5 | I502: 39.47244629205207 | J502: -0.36738764730123064
A503: Celeritas | B503: Convenience stores | C503: Private | D503: Premises | E503: Valecia | F503: 46001 | G503: Merceria Lana Negra | H503: C. de Huesca, 6 | I503: 39.46957741762155 | J503: -0.3804449349056476
A504: Celeritas | B504: Convenience stores | C504: Private | D504: Kiosk | E504: Valecia | F504: 46007 | G504: Kiosco Guillen De Castro | H504: C/ Guillem de Castro, 55 | I504: 39.470481889709696 | J504: -0.3832721019181088
A505: Celeritas | B505: Convenience stores | C505: Private | D505: Premises | E505: Valecia | F505: 46008 | G505: Bazar 28 De Septiembre | H505: C/ Guillem de Castro, 69 | I505: 39.47136589622819 | J505: -0.3839602588172939
A506: Celeritas | B506: Convenience stores | C506: Private | D506: Premises | E506: Valecia | F506: 46008 | G506: Candy | H506: Gran Vía de Fernando el Católico, 34 | I506: 39.47254225565486 | J506: -0.3859083159766075
A507: Celeritas | B507: Convenience stores | C507: Private | D507: Premises | E507: Valecia | F507: 46008 | G507: Expendeduria 156 | H507: C. de Calixto III, 1 | I507: 39.4721772951249 | J507: -0.38683104776201443
A508: Celeritas | B508: Convenience stores | C508: Private | D508: Premises | E508: Valecia | F508: 46008 | G508: Estanco Valencia 85 | H508: Av. de Pérez Galdós, 100 | I508: 39.471066370384285 | J508: -0.3925271334269611
A509: Celeritas | B509: Convenience stores | C509: Private | D509: Premises | E509: Valecia | F509: 46003 | G509: Naturalworld | H509: Pl. de los Fueros, 1 | I509: 39.47904901005767 | J509: -0.3763810218837944
A510: Celeritas | B510: Convenience stores | C510: Private | D510: Premises | E510: Valecia | F510: 46008 | G510: Joisfe | H510: C. del Historiador Sanchis Sivera, 24 | I510: 39.46874502509329 | J510: -0.38731127900024404
A511: Celeritas | B511: Convenience stores | C511: Private | D511: Premises | E511: Valecia | F511: 46005 | G511: Estanco Prensa C/ Joaquin Costa 44 | H511: C. Joaquín Costa, 44 | I511: 39.46458378558827 | J511: -0.36622210881977557
A512: Celeritas | B512: Convenience stores | C512: Private | D512: Premises | E512: Valecia | F512: 46005 | G512: Doctor Manzana | H512: Av. del Reino de Valencia, 18 | I512: 39.46447880097586 | J512: -0.3715899939196278
... A793: GLS | B793: Convenience stores | C793: Private | D793: Premises | E793: Valencia | F793: 46035 | G793: Ps Bambini Moda Infantil Y Mujer | H793: C / Campamento 44 bajo | I793: 39.50226890615729 | J793: -0.4220765706309232
...

Sheet City ​​of Barcelona
B2: Company | C2: Type | D2: Infrastructure | E2: Type Infrastructure | F2: City | G2: Zip Code | H2: Location | I2: Address | J2: Latitude | K2: Longitude
B4: InPost | C4: Convenience stores | D4: Private | E4: Premises | F4: Barcelona | G4: 8001 | H4: Mobil Mania | I4: Rambla del Raval, 6 | J4: 41.379004 | K4: 2.1686181
B5: InPost | C5: Convenience stores | D5: Private | E5: Premises | F5: Barcelona | G5: 8001 | H5: Impremta Sebtor | I5: Carrer de l'Hospital, 157 | J5: 41.379647 | K5: 2.1664182
B6: InPost | C6: Lockers | D6: Private | E6: Parking | F6: Barcelona | G6: 8001 | H6: Lockers 24/7 Saba Illa Raval Bar | I6: C. de San Rafael, 15 | J6: 41.379093 | K6: 2.170133
B7: InPost | C7: Convenience stores | D7: Private | E7: Premises | F7: Barcelona | G7: 8001 | H7: Copisteria Geografia Ub | I7: Carrer de les Ramelleres, 21 | J7: 41.384566 | K7: 2.1683374
B8: InPost | C8: Convenience stores | D8: Private | E8: Premises | F8: Barcelona | G8: 8001 | H8: Copywork | I8: C. de Joaquín Costa, 2 | J8: 41.381177 | K8: 2.1675444
B9: InPost | C9: Convenience stores | D9: Private | E9: Premises | F9: Barcelona | G9: 8001 | H9: Madiha Fashion | I9: Carrer Nou de la Rambla, 22 | J9: 41.378721 | K9: 2.1734232
B10: InPost | C10: Convenience stores | D10: Private | E10: Kiosk | F10: Barcelona | G10: 8001 | H10: Kiosco De Prensa | I10: Rda. de Sant Antoni, 100 | J10: 41.385135 | K10: 2.164182
B11: InPost | C11: Convenience stores | D11: Private | E11: Premises | F11: Barcelona | G11: 8001 | H11: Copypelai | I11: Carrer de Pelai, 9 | J11: 41.386088 | K11: 2.1665315
B12: InPost | C12: Convenience stores | D12: Private | E12: Premises | F12: Barcelona | G12: 8001 | H12: Phonix The Smart Point | I12: Carrer de Jovellanos, 1 | J12: 41.385091 | K12: 2.1678865
B13: InPost | C13: Convenience stores | D13: Private | E13: Premises | F13: Barcelona | G13: 8001 | H13: Fiber Sonic | I13: Carrer del Tigre, 33 | J13: 41.382352 | K13: 2.1638637
B14: InPost | C14: Convenience stores | D14: Private | E14: Premises | F14: Barcelona | G14: 8002 | H14: Taha Mobile Shop | I14: Carrer d'Avinyó, 29 | J14: 41.380705 | K14: 2.1784414
B15: InPost | C15: Convenience stores | D15: Private | E15: Premises | F15: Barcelona | G15: 8002 | H15: Te Habla Mobile Mobile | I15: Carrer de Josep Anselm Clavé, 27 | J15: 41.378192 | K15: 2.1780974
... B2295: Amazon | C2295: Estación logistica de ultima milla | D2295: Private | E2295: industrial estate | F2295: Barcelona | G2295: 8210 | H2295: DCT4 Amazon - Última milla / Amazon Logistics Station | I2295: Av. de Can Rosés, 9 Rubí | J2295: 41.505545 | K2295: 2.041015
B2296: Amazon | C2296: Centros de distribución/recepción | D2296: Private | E2296: industrial estate | F2296: Barcelona | G2296: 8100 | I2296: Carrer de Facundo Bacardí, 10, Mollet del Vallès | J2296: 41.551732 | K2296: 2.2301543
B2297: Amazon | C2297: Estación logistica de ultima milla | D2297: Private | E2297: industrial estate | F2297: Barcelona | G2297: 8110 | I2297: Carrer Fresser, Montcada i Reixac | J2297: 41.501999 | K2297: 2.1897093
B2298: Correos | C2298: Estación logistica de ultima milla | D2298: Public | E2298: Industrial estate | F2298: Barcelona | G2298: 8174 | H2298: (CTA) Centro de distribución urbana o estación de última milla | I2298: Carrer del Danubi, 12, Sant Cugat del Vallès | J2298: 41.487303 | K2298: 2.0496882
B2299: Correos | C2299: Estación logistica de ultima milla | D2299: Public | E2299: Industrial estate | F2299: Barcelona | G2299: 8040 | H2299: (CTA) Centro de distribución urbana o estación de última milla | I2299: Carrer Número 29, 12, Sants-Montjuïc | J2299: 41.33884 | K2299: 2.1276809
B2300: Correos | C2300: Estación logistica de ultima milla | D2300: Public | E2300: Industrial estate | F2300: Barcelona | G2300: 8038 | I2300: Passeig Josep Carner, 33, Sants-Montjuïc | J2300: 41.372343 | K2300: 2.1755215
B2301: Correos | C2301: Centros de distribución/recepción | D2301: Public | E2301: Industrial estate | F2301: Barcelona | G2301: 8820 | I2301: Carrer de Estel Polar, 5, El Prat de Llobregat | J2301: 41.299485 | K2301: 2.064535
B2302: Correos Express | C2302: Estación logistica de ultima milla | D2302: Public | E2302: Industrial estate | F2302: Barcelona | G2302: 8830 | H2302: Centro de distribución urbana o estación de última milla | I2302: Carrer dels Filats, Nave 4, 08830 Sant Boi de Llobregat | J2302: 41.325119 | K2302: 2.0421193
B2303: Correos Express | C2303: Centros de distribución/recepción | D2303: Public | E2303: Industrial estate | F2303: Barcelona | G2303: 8130 | H2303: Plataformas de consolidación y reparto provincial. | I2303: Carrer de Can Banús, S/N, Santa Perpètua de Mogoda | J2303: 41.537805 | K2303: 2.1868651
B2304: Mondial Relay (Impost) | C2304: Estación logistica de ultima milla | D2304: Private | E2304: Industrial estate | F2304: Barcelona | G2304: 8800 | H2304: Centro de distribución urbana o estación de última milla | I2304: Carrer de les Oliveres, 1, 08800 Vilanova i la Geltrú | J2304: 41.245688 | K2304: 1.7237655
B2305: Seur | C2305: Centros de distribución/recepción | D2305: Private | E2305: Industrial estate | F2305: Barcelona | G2305: 8820 | H2305: Almacenamiento y cross-docking | I2305: Carrer Cal Nyepa, 23-27, 08820, Barcelona | J2305: 41.316114 | K2305: 2.1410141
B2306: Seur | C2306: Estación logistica de ultima milla | D2306: Private | E2306: Industrial estate | F2306: Barcelona | G2306: 8821 | H2306: Centro de distribución urbana o estación de última milla | I2306: Carrer Cal Fernando, 25, 08820 El Prat de Llobregat, Barcelona | J2306: 41.316196 | K2306: 2.140989
B2307: Seur | C2307: Centros de distribución/recepción | D2307: Private | E2307: Industrial estate | F2307: Barcelona | G2307: 8243 | I2307: Carrer de Ramon Farguell, 62, 08243 Manresa, Barcelona | J2307: 41.709494 | K2307: 1.8517822
B2308: Seur | C2308: Centros de distribución/recepción | D2308: Private | E2308: Industrial estate | F2308: Barcelona | G2308: 8210 | I2308: Poligono Industrial Can Salvatella, Av. Torre de Mateu, 93, 08210 Barberà del Vallès, Barcelona | J2308: 41.512914 | K2308: 2.1562297
B2309: DHL | C2309: Centros de distribución/recepción | D2309: Private | E2309: Industrial estate | F2309: Barcelona | G2309: 8820 | H2309: Almacenamiento y cross-docking | I2309: C/ L'Estany de la Messeguera, 14-24, El Prat de Llobregat | J2309: 41.319881 | K2309: 2.1359299
B2310: DHL | C2310: Centros de distribución/recepción | D2310: Private | E2310: Industrial estate | F2310: Barcelona | G2310: 8170 | H2310: Almacenamiento y cross-docking (Grandes Clientes) | I2310: Carrer d'Edison, 2, 08170 Montornès del Vallès | J2310: 41.557648 | K2310: 2.2609325
B2311: DHL | C2311: Estación logistica de ultima milla | D2311: Private | E2311: Industrial estate | F2311: Barcelona | G2311: 8130 | H2311: Centro de distribución urbana o estación de última milla | I2311: CIM del Valles, Santa Perpètua de Mogoda | J2311: 41.539973 | K2311: 2.1839371
B2312: DHL | C2312: Estación logistica de ultima milla | D2312: Private | E2312: Industrial estate | F2312: Tarragona | G2312: 43120 | H2312: Centro de distribución urbana o estación de última milla | I2312: Avinguda de les Puntes, Illa 6, Constantí, Tarragona | J2312: 41.164565 | K2312: 1.1590294
B2313: DHL | C2313: Centros de distribución/recepción | D2313: Private | E2313: Industrial estate | F2313: Barcelona | G2313: 8755 | I2313: Carrer Manganès, 3, Castellbisbal | J2313: 41.468075 | K2313: 1.952375
B2314: DHL | C2314: Centros de distribución/recepción | D2314: Private | E2314: Industrial estate | F2314: Barcelona | G2314: 8820 | I2314: C. Cal Truco, 50-60, 08820 El Prat de Llobregat | J2314: 41.314789 | K2314: 2.1410618
B2315: DHL | C2315: Centros de distribución/recepción | D2315: Private | E2315: Industrial estate | F2315: Barcelona | G2315: 8040 | I2315: Carrer de l'Atlàntic, 109, Sants-Montjuïc | J2315: 41.326815 | K2315: 2.1420242
B2316: DHL Express | C2316: Centros de distribución/recepción | D2316: Private | E2316: Industrial estate | F2316: Barcelona | G2316: 8820 | H2316: Consolidación internacional de exportaciones e importaciones | I2316: Aeropuerto de El Prat, Carrer de Estel Polar, 9332 | J2316: 41.298654 | K2316: 2.0635465
B2317: Fedex | C2317: Estación logistica de ultima milla | D2317: Private | E2317: Industrial estate | F2317: Barcelona | G2317: 8040 | H2317: Centro de distribución urbana o estación de última milla | I2317: Carrer Número 21, Sants-Montjuïc | J2317: 41.340491 | K2317: 2.1428507
B2318: Fedex | C2318: Centros de distribución/recepción | D2318: Private | E2318: Industrial estate | F2318: Barcelona | G2318: 8820 | H2318: Recogida y agrupacion de paquetes (tráfico aéreo o intermodal) | I2318: Carrer de Estel Polar, S/N | J2318: 41.297898 | K2318: 2.0602266
B2319: Celeritas | C2319: Centros de distribución/recepción | D2319: Private | E2319: Industrial estate | F2319: Barcelona | G2319: 8040 | H2319: Opera mediante almacenes de terceros en Barcelona | I2319: Sector C, Calle K (Zona Franca) | J2319: 41.327963 | K2319: 2.1134741
B2320: GLS | C2320: Centros de distribución/recepción | D2320: Private | E2320: Industrial estate | F2320: Barcelona | G2320: 8349 | H2320: Centro de distribución regional para reparto comarcal | I2320: Rda. Narcís Monturiol, 23-B, Cabrera de Mar | J2320: 41.529767 | K2320: 2.4147957
B2321: GLS | C2321: Centros de distribución/recepción | D2321: Private | E2321: Industrial estate | F2321: Barcelona | G2321: 8302 | H2321: Centro de distribución urbana o estación de última milla | I2321: Carrer de la Repuntadora, 45, Mataró | J2321: 41.528192 | K2321: 2.4269597
B2322: GLS | C2322: Estación logistica de ultima milla | D2322: Private | E2322: Industrial estate | F2322: Barcelona | G2322: 8918 | H2322: Almacenamiento y cross-docking | I2322: Carrer d'Eduard Maristany, 384, Badalona | J2322: 41.431169 | K2322: 2.2354852
B2323: GLS | C2323: Estación logistica de ultima milla | D2323: Private | E2323: Industrial estate | F2323: Barcelona | G2323: 8917 | H2323: Almacenamiento y cross-docking | I2323: 08917 Badalona, Barcelona | J2323: 41.460582 | K2323: 2.224293
B2324: GLS | C2324: Centros de distribución/recepción | D2324: Private | E2324: Industrial estate | F2324: Barcelona | G2324: 8130 | H2324: Mini-hub provincial | I2324: Carrer H, 32, 08130 Santa Perpètua de Mogoda | J2324: 41.533138 | K2324: 2.192959
B2325: GLS | C2325: Estación logistica de ultima milla | D2325: Private | E2325: Industrial estate | F2325: Barcelona | G2325: 8908 | I2325: Carrer Miguel Hernández, 112, 114, L'Hospitalet de Llobregat | J2325: 41.351196 | K2325: 2.1212816
B2326: GLS | C2326: Estación logistica de ultima milla | D2326: Private | E2326: Industrial estate | F2326: Barcelona | G2326: 8908 | I2326: C. de Pablo Iglesias, 102-112, L'Hospitalet de Llobregat | J2326: 41.346781 | K2326: 2.1248106
B2327: Mail Boxes ETC | C2327: Estación logistica de ultima milla | D2327: Private | E2327: Industrial estate | F2327: Barcelona | H2327: Almacenaje, picking, embalaje pedidos, gestión inventario | I2327: s/d | J2327: s/d | K2327: s/d
B2328: CTT Express | C2328: Centros de distribución/recepción | D2328: Private | E2328: Industrial estate | F2328: Barcelona | G2328: 8130 | H2328: Plataformas logística regional | I2328: Carrer H, 11, 08130 Santa Perpètua de Mogoda | J2328: 41.533105 | K2328: 2.191154
B2329: CTT Express | C2329: Estación logistica de ultima milla | D2329: Private | E2329: Industrial estate | F2329: Barcelona | G2329: 8830 | H2329: Centro de distribución urbana o estación de última milla | I2329: Carrer dels Feixars, 08830 Sant Boi de Llobregat | J2329: 41.325839 | K2329: 2.0458221
B2330: UPS | C2330: Estación logistica de ultima milla | D2330: Private | E2330: Industrial estate | F2330: Barcelona | G2330: 8040 | H2330: Centro logístico de entrada/salida urbana | I2330: Carrer Número 2, 1-13, Sants-Montjuïc | J2330: 41.342134 | K2330: 2.1405079
B2331: UPS | C2331: Estación logistica de ultima milla | D2331: Private | E2331: Industrial estate | F2331: Barcelona | G2331: 8040 | H2331: Centro de distribución urbana o estación de última milla | I2331: Carrer Número 21, Sants-Montjuïc | J2331: 41.34303 | K2331: 2.1387068
B2332: Nacex | C2332: Estación logistica de ultima milla | D2332: Private | E2332: Industrial estate | F2332: Barcelona | G2332: 8908 | H2332: Centro de distribución urbana o estación de última milla | I2332: Calle Pablo Iglesias, 112-122 , L'Hospitalet de Llobregat | J2332: 41.346631 | K2332: 2.1238017
B2333: Nacex | C2333: Centros de distribución/recepción | D2333: Private | E2333: Industrial estate | F2333: Barcelona | G2333: 8940 | H2333: Centro de distribución urbana o estación de última milla | I2333: Ctra. de l'Hospitalet, 17, nave B, Cornellà de Llobregat | J2333: 41.353928 | K2333: 2.07894
B2334: Nacex | C2334: Centros de distribución/recepción | D2334: Private | E2334: Industrial estate | F2334: Barcelona | G2334: 8980 | H2334: Almacenamiento y cross-docking | I2334: Carrer d'Armenteres, 14, Nave 6, Matacàs | J2334: 41.375583 | K2334: 2.0444141
B2335: MRW | C2335: Centros de distribución/recepción | D2335: Private | E2335: Industrial estate | F2335: Barcelona | G2335: 8830 | H2335: Hub principal de MRW | I2335: Av. les Garrigues, 45 | J2335: 41.308788 | K2335: 2.0657144
B2336: MRW | C2336: Centros de distribución/recepción | D2336: Private | E2336: Industrial estate | F2336: Barcelona | G2336: 8150 | H2336: Centro de distribución comarcal | I2336: Carrer Molí de Vent, 2, Parets del Vallès | J2336: 41.587337 | K2336: 2.2434108
B2337: MRW | C2337: Centros de distribución/recepción | D2337: Private | E2337: Industrial estate | F2337: Barcelona | G2337: 8520 | H2337: Centro de distribución urbana o estación de última milla | I2337: Carrer Mas Pujol, 16 | J2337: 41.631982 | K2337: 2.29027
B2338: Cainiao (AliExpress) | C2338: Centros de distribución/recepción | D2338: Private | E2338: Industrial estate | F2338: Barcelona | G2338: s/d | H2338: Clasificación local de paquetes; entrega de última milla | I2338: Zona industrial de Barcelona | J2338: 41.333166 | K2338: 2.1392511
B2339: Zeleris | C2339: Centros de distribución/recepción | D2339: Private | E2339: Industrial estate | F2339: Barcelona | G2339: 8130 | I2339: Carrer Vallès, 16, 08130 Santa Perpètua de Mogoda | J2339: 41.549455 | K2339: 2.1799604
B2340: Envialia | C2340: Centros de distribución/recepción | D2340: Private | E2340: Industrial estate | F2340: Barcelona | G2340: 8820 | I2340: Avinguda de l'Estany de la Messeguera, 30 | J2340: 41.318605 | K2340: 2.1389859

Sheet Sheet2
A1: Company | B1: Type | C1: Infrastructure | D1: Type Infrastructure | E1: City | F1: Zip Code | G1: Location | H1: Address | I1: Latitude | J1: Longitude | L1: Type | M1: Count of Company
A2: InPost | B2: Convenience stores | C2: Private | D2: Premises | E2: Barcelona | F2: 8001 | G2: Mobil Mania | H2: Rambla del Raval, 6 | I2: 41.379004 | J2: 2.1686181 | L2: Click&Collect | M2: 97
A3: InPost | B3: Convenience stores | C3: Private | D3: Premises | E3: Barcelona | F3: 8001 | G3: Impremta Sebtor | H3: Carrer de l'Hospital, 157 | I3: 41.379647 | J3: 2.1664182 | L3: Convenience stores | M3: 1541
A4: InPost | B4: Lockers | C4: Private | D4: Parking | E4: Barcelona | F4: 8001 | G4: Lockers 24/7 Saba Illa Raval Bar | H4: C. de San Rafael, 15 | I4: 41.379093 | J4: 2.170133 | L4: Lockers | M4: 504
A5: InPost | B5: Convenience stores | C5: Private | D5: Premises | E5: Barcelona | F5: 8001 | G5: Copisteria Geografia Ub | H5: Carrer de les Ramelleres, 21 | I5: 41.384566 | J5: 2.1683374 | L5: LSP PUDOs | M5: 109
A6: InPost | B6: Convenience stores | C6: Private | D6: Premises | E6: Barcelona | F6: 8001 | G6: Copywork | H6: C. de Joaquín Costa, 2 | I6: 41.381177 | J6: 2.1675444 | L6: Total general | M6: 2251
A7: InPost | B7: Convenience stores | C7: Private | D7: Premises | E7: Barcelona | F7: 8001 | G7: Madiha Fashion | H7: Carrer Nou de la Rambla, 22 | I7: 41.378721 | J7: 2.1734232
A8: InPost | B8: Convenience stores | C8: Private | D8: Kiosk | E8: Barcelona | F8: 8001 | G8: Kiosco De Prensa | H8: Rda. de Sant Antoni, 100 | I8: 41.385135 | J8: 2.164182
A9: InPost | B9: Convenience stores | C9: Private | D9: Premises | E9: Barcelona | F9: 8001 | G9: Copypelai | H9: Carrer de Pelai, 9 | I9: 41.386088 | J9: 2.1665315
A10: InPost | B10: Convenience stores | C10: Private | D10: Premises | E10: Barcelona | F10: 8001 | G10: Phonix The Smart Point | H10: Carrer de Jovellanos, 1 | I10: 41.385091 | J10: 2.1678865
A11: InPost | B11: Convenience stores | C11: Private | D11: Premises | E11: Barcelona | F11: 8001 | G11: Fiber Sonic | H11: Carrer del Tigre, 33 | I11: 41.382352 | J11: 2.1638637
A12: InPost | B12: Convenience stores | C12: Private | D12: Premises | E12: Barcelona | F12: 8002 | G12: Taha Mobile Shop | H12: Carrer d'Avinyó, 29 | I12: 41.380705 | J12: 2.1784414
A13: InPost | B13: Convenience stores | C13: Private | D13: Premises | E13: Barcelona | F13: 8002 | G13: Te Habla Mobile Mobile | H13: Carrer de Josep Anselm Clavé, 27 | I13: 41.378192 | J13: 2.1780974
A14: InPost | B14: Convenience stores | C14: Private | D14: Premises | E14: Barcelona | F14: 8002 | G14: Libreria Balmes | H14: Carrer de Duran i Bas, 11 | I14: 41.385813 | J14: 2.1745732
A15: InPost | B15: Convenience stores | C15: Private | D15: Premises | E15: Barcelona | F15: 8003 | G15: Estanc Bcn 159 | H15: Placeta de Montcada, 6 | I15: 41.384551 | J15: 2.1819846
A16: InPost | B16: Lockers | C16: Private | D16: Parking | E16: Barcelona | F16: 8003 | G16: Lockers 24/7 Saba Barceloneta Ba | H16: Carrer del Baluard, 27S | I16: 41.380092 | J16: 2.1890562
A17: InPost | B17: Convenience stores | C17: Private | D17: Premises | E17: Barcelona | F17: 8003 | G17: Punto Y Coma | H17: Carrer De Pepe Rubianes 12 | I17: 41.378379 | J17: 2.1893178
A18: InPost | B18: Convenience stores | C18: Private | D18: Premises | E18: Barcelona | F18: 8003 | G18: Instalaciones De La Fuente | H18: Carrer de la Mediterrània, 4 | I18: 41.382051 | J18: 2.1889039
... A2252: MRW | B2252: LSP PUDOs | C2252: Private | D2252: Premises | E2252: Barcelona | F2252: 8020 | G2252: Oficina Mrw 00637 | H2252: Rambla De Prim, 246 | I2252: 41.425173 | J2252: 2.2017844

Sheet Datos
B2: Ciudad | C2: Nº puntos por tipo | H2: Infrastructure | K2: Type Infrastructure | T2: Total
C4: Convenience stores | D4: Lockers | E4: Click&Collect | F4: LSP PUDOs | H4: Public | I4: Private | K4: Supermarket | L4: Parking | M4: Premises | N4: Kiosk | O4: Service Station | P4: Public facility | Q4: Public Infrastructure | R4: Mall | S4: Gym | T4: =SUM(T6+T11+T16) -> 6545
B6: Madrid | C6: =COUNTIF('City ​​of Madrid'!C4:C3285,Datos!C4) -> 2216 | D6: =COUNTIF('City ​​of Madrid'!C4:C3285,Datos!D4) -> 719 | E6: =COUNTIF('City ​​of Madrid'!C4:C3285,Datos!E4) -> 146 | F6: =COUNTIF('City ​​of Madrid'!C4:C3285,Datos!F4) -> 200 | H6: =COUNTIF('City ​​of Madrid'!D4:D3285,Datos!H4) -> 219 | I6: =COUNTIF('City ​​of Madrid'!D4:D3285,Datos!I4) -> 3061 | K6: =COUNTIF('City ​​of Madrid'!$E$4:$E$3285,Datos!K4) -> 178 | L6: =COUNTIF('City ​​of Madrid'!$E$4:$E$3285,Datos!L4) -> 111 | M6: =COUNTIF('City ​​of Madrid'!$E$4:$E$3285,Datos!M4) -> 2576 | N6: =COUNTIF('City ​​of Madrid'!$E$4:$E$3285,Datos!N4) -> 64 | O6: =COUNTIF('City ​​of Madrid'!$E$4:$E$3285,Datos!O4) -> 84 | P6: =COUNTIF('City ​​of Madrid'!$E$4:$E$3285,Datos!P4) -> 178 | Q6: =COUNTIF('City ​​of Madrid'!$E$4:$E$3285,Datos!Q4) -> 14 | R6: =COUNTIF('City ​​of Madrid'!$E$4:$E$3285,Datos!R4) -> 64 | S6: =COUNTIF('City ​​of Madrid'!$E$4:$E$3285,Datos!S4) -> 4 | T6: =SUM(C6:F6) -> 3281
C8: =C6/T6 -> 0.67540384 | D8: =D6/T6 -> 0.21914051 | E8: =E6/T6 -> 0.044498628 | F8: =F6/T6 -> 0.060957025 | H8: =H6/T6 -> 0.066747943 | I8: =I6/$T$6 -> 0.93294727 | K8: =K6/$T$6 -> 0.054251753 | L8: =L6/$T$6 -> 0.033831149 | M8: =M6/$T$6 -> 0.78512649 | N8: =N6/$T$6 -> 0.019506248 | O8: =O6/$T$6 -> 0.025601951 | P8: =P6/$T$6 -> 0.054251753 | Q8: =Q6/$T$6 -> 0.0042669918 | R8: =R6/$T$6 -> 0.019506248 | S8: =S6/$T$6 -> 0.0012191405
B11: Valencia | C11: =COUNTIF('City ​​of Valencia'!C4:C985,Datos!C4) -> 777 | D11: =COUNTIF('City ​​of Valencia'!C4:C985,Datos!D4) -> 133 | E11: =COUNTIF('City ​​of Valencia'!C4:C985,Datos!E4) -> 24 | F11: =COUNTIF('City ​​of Valencia'!C4:C985,Datos!F4) -> 48 | H11: =COUNTIF('City ​​of Valencia'!D4:D985,Datos!H4) -> 43 | I11: =COUNTIF('City ​​of Valencia'!D4:D985,Datos!I4) -> 939 | K11: =COUNTIF('City ​​of Valencia'!$E$4:$E$985,Datos!K4) -> 45 | L11: =COUNTIF('City ​​of Valencia'!$E$4:$E$985,Datos!L4) -> 17 | M11: =COUNTIF('City ​​of Valencia'!$E$4:$E$985,Datos!M4) -> 745 | N11: =COUNTIF('City ​​of Valencia'!$E$4:$E$985,Datos!N4) -> 93 | O11: =COUNTIF('City ​​of Valencia'!$E$4:$E$985,Datos!O4) -> 26 | P11: =COUNTIF('City ​​of Valencia'!$E$4:$E$985,Datos!P4) -> 39 | Q11: =COUNTIF('City ​​of Valencia'!$E$4:$E$985,Datos!Q4) -> 4 | R11: =COUNTIF('City ​​of Valencia'!$E$4:$E$985,Datos!R4) -> 9 | S11: =COUNTIF('City ​​of Valencia'!$E$4:$E$985,Datos!S4) -> 3 | T11: =SUM(C11:F11) -> 982
C13: =C11/T11 -> 0.79124236 | D13: =D11/T11 -> 0.13543788 | E13: =E11/T11 -> 0.024439919 | F13: =F11/T11 -> 0.048879837 | H13: =H11/T11 -> 0.043788187 | I13: =I11/$T$11 -> 0.95621181 | K13: =K11/$T$11 -> 0.045824847 | L13: =L11/$T$11 -> 0.017311609 | M13: =M11/$T$11 -> 0.7586558 | N13: =N11/$T$11 -> 0.094704684 | O13: =O11/$T$11 -> 0.026476578 | P13: =P11/$T$11 -> 0.039714868 | Q13: =Q11/$T$11 -> 0.0040733198 | R13: =R11/$T$11 -> 0.0091649695 | S13: =S11/$T$11 -> 0.0030549898
B16: Barcelona | C16: =COUNTIF('City ​​of Barcelona'!C4:C2285,C4) -> 1549 | D16: =COUNTIF('City ​​of Barcelona'!C4:C2285,D4) -> 524 | E16: =COUNTIF('City ​​of Barcelona'!C4:C2285,E4) -> 97 | F16: =COUNTIF('City ​​of Barcelona'!C4:C2285,F4) -> 112 | H16: =COUNTIF('City ​​of Barcelona'!D4:D2285,H4) -> 118 | I16: =COUNTIF('City ​​of Barcelona'!D4:D2285,I4) -> 2164 | K16: =COUNTIF('City ​​of Barcelona'!$E$4:$E$2285,K4) -> 148 | L16: =COUNTIF('City ​​of Barcelona'!$E$4:$E$2285,L4) -> 217 | M16: =COUNTIF('City ​​of Barcelona'!$E$4:$E$2285,M4) -> 1652 | N16: =COUNTIF('City ​​of Barcelona'!$E$4:$E$2285,N4) -> 104 | O16: =COUNTIF('City ​​of Barcelona'!$E$4:$E$2285,O4) -> 46 | P16: =COUNTIF('City ​​of Barcelona'!$E$4:$E$2285,P4) -> 76 | Q16: =COUNTIF('City ​​of Barcelona'!$E$4:$E$2285,Q4) -> 20 | R16: =COUNTIF('City ​​of Barcelona'!$E$4:$E$2285,R4) -> 16 | S16: =COUNTIF('City ​​of Barcelona'!$E$4:$E$2285,S4) -> 1 | T16: =SUM(C16:F16) -> 2282
C18: =C16/T16 -> 0.67879053 | D18: =D16/T16 -> 0.22962314 | E18: =E16/T16 -> 0.042506573 | F18: =F16/T16 -> 0.049079755 | H18: =H16/T16 -> 0.051709027 | I18: =I16/$T$16 -> 0.94829097 | K18: =K16/$T$16 -> 0.06485539 | L18: =L16/$T$16 -> 0.095092025 | M18: =M16/$T$16 -> 0.72392638 | N18: =N16/$T$16 -> 0.045574058 | O18: =O16/$T$16 -> 0.020157756 | P18: =P16/$T$16 -> 0.033304119 | Q18: =Q16/$T$16 -> 0.0087642419 | R18: =R16/$T$16 -> 0.0070113935 | S18: =S16/$T$16 -> 0.00043821209
B23: Ciudad | C23: Nº Códigos Postales | D23: Nº Empresas | E23: Nº tipos de infraestructura
B25: Madrid | C25: {=SUM(1/COUNTIF('City ​​of Madrid'!G4:G3285,'City ​​of Madrid'!G4:G3285))} -> 75 | D25: {=SUM(1/COUNTIF('City ​​of Madrid'!B4:B3285,'City ​​of Madrid'!B4:B3285))} -> 13 | E25: {=SUM(1/COUNTIF('City ​​of Madrid'!E4:E3285,'City ​​of Madrid'!E4:E3285))} -> 11
B28: Valencia | C28: {=SUM(1/COUNTIF('City ​​of Valencia'!G4:G985,'City ​​of Valencia'!G4:G985))} -> 29 | D28: {=SUM(1/COUNTIF('City ​​of Valencia'!B4:B985,'City ​​of Valencia'!B4:B985))} -> 13 | E28: {=SUM(1/COUNTIF('City ​​of Valencia'!E4:E985,'City ​​of Valencia'!E4:E985))} -> 10
B31: Barcelona | C31: {=SUM(1/COUNTIF('City ​​of Barcelona'!G4:G2285,'City ​​of Barcelona'!G4:G2285))} -> 60 | D31: {=SUM(1/COUNTIF('City ​​of Barcelona'!B4:B2285,'City ​​of Barcelona'!B4:B2285))} -> 13 | E31: {=SUM(1/COUNTIF('City ​​of Barcelona'!E4:E2285,'City ​​of Barcelona'!E4:E2285))} -> 10
B37: Ciudad | C37: InPost | D37: Correos | E37: Amazon | F37: Seur | G37: DHL | H37: Celeritas | I37: CTT Express | J37: GLS | K37: Mail Boxes ETC | L37: Nacex | M37: UPS | N37: Drop Point Systems | O37: PUDO | P37: MRW | Q37: Totales
B39: Orden Empresa | C39: 2º | D39: 8º | E39: 1º | F39: 3º | G39: 7º | H39: 6º | I39: 4º | J39: 10º | K39: 12º | L39: 11º | M39: 5º | N39: 14º | O39: 9º | P39: 13º
C40: =C42/$Q$42 -> #REF! | D40: =D42/$Q$42 -> #REF! | E40: =E42/$Q$42 -> #REF! | F40: =F42/$Q$42 -> #REF! | G40: =G42/$Q$42 -> #REF! | H40: =H42/$Q$42 -> #REF! | I40: =I42/$Q$42 -> #REF! | J40: =J42/$Q$42 -> #REF! | ... P40: =P42/$Q$42 -> #REF! | Q40: =SUM(C40:P40) -> #REF!
B42: Total Puntos B2C Empresa | C42: =SUM(C75:C78) -> 1044 | D42: =SUM(D75:D78) -> 260 | E42: =SUM(E75:E78) -> 1092 | F42: =SUM(F75:F78) -> 1025 | G42: =SUM(G75:G78) -> 271 | H42: =SUM(H75:H78) -> 319 | I42: =SUM(I75:I78) -> 783 | J42: =SUM(J75:J78) -> 162 | ... P42: =SUM(P75:P78) -> 30 | Q42: =SUM(C42:P42) -> #REF!
B44: Madrid | U44: Media 3 ciudades
B46: Convenience stores | C46: =COUNTIF('City ​​of Madrid'!$C$4:$C$592,Datos!B46) -> 463 | D46: =COUNTIF('City ​​of Madrid'!$C$609:$C$770,Datos!B46) -> 0 | E46: =COUNTIF('City ​​of Madrid'!$C$772:$C$1323,Datos!B46) -> 304 | F46: =COUNTIF('City ​​of Madrid'!$C$1324:$C$1920,Datos!B46) -> 374 | G46: =COUNTIF('City ​​of Madrid'!$C$1927:$C$2045,Datos!B46) -> 111 | H46: =COUNTIF('City ​​of Madrid'!$C$2069:$C$2211,Datos!B46) -> 143 | I46: =COUNTIF('City ​​of Madrid'!$C$2227:$C$2621,Datos!B46) -> 395 | J46: =COUNTIF('City ​​of Madrid'!$C$2625:$C$2695,Datos!B46) -> 59 | K46: =COUNTIF('City ​​of Madrid'!$C$2764:$C$2773,Datos!B46) -> 0 | L46: =COUNTIF('City ​​of Madrid'!$C$2780:$C$2814,Datos!B46) -> 27 | M46: =COUNTIF('City ​​of Madrid'!$C$2923:$C$3100,Datos!B46) -> 148 | N46: =COUNTIF(#REF!,Datos!B46) -> #REF! | O46: =COUNTIF('City ​​of Madrid'!$C$3114:$C$3182,Datos!B46) -> 0 | P46: =COUNTIF('City ​​of Madrid'!$C$3260:$C$3267,Datos!B46) -> 0 | Q46: =SUM(C46:P46) -> #REF! | R46: 1º | S46: =Q46/$Q$51 -> #REF! | U46: Convenience stores | W46: =(S46+S55+S64)/3 -> #REF!
B47: Lockers | C47: =COUNTIF('City ​​of Madrid'!$C$4:$C$592,Datos!B47) -> 125 | D47: =COUNTIF('City ​​of Madrid'!$C$609:$C$770,Datos!B47) -> 73 | E47: =COUNTIF('City ​​of Madrid'!$C$772:$C$1323,Datos!B47) -> 248 | F47: =COUNTIF('City ​​of Madrid'!$C$1324:$C$1920,Datos!B47) -> 217 | G47: =COUNTIF('City ​​of Madrid'!$C$1927:$C$2045,Datos!B47) -> 0 | H47: =COUNTIF('City ​​of Madrid'!$C$2069:$C$2211,Datos!B47) -> 0 | I47: =COUNTIF('City ​​of Madrid'!$C$2227:$C$2621,Datos!B47) -> 0 | J47: =COUNTIF('City ​​of Madrid'!$C$2625:$C$2695,Datos!B47) -> 2 | K47: =COUNTIF('City ​​of Madrid'!$C$2764:$C$2773,Datos!B47) -> 0 | L47: =COUNTIF('City ​​of Madrid'!$C$2780:$C$2814,Datos!B47) -> 0 | M47: =COUNTIF('City ​​of Madrid'!$C$2923:$C$3100,Datos!B47) -> 30 | N47: =COUNTIF(#REF!,Datos!B47) -> #REF! | O47: =COUNTIF('City ​​of Madrid'!$C$3114:$C$3182,Datos!B47) -> 0 | P47: =COUNTIF('City ​​of Madrid'!$C$3260:$C$3267,Datos!B47) -> 0 | Q47: =SUM(C47:P47) -> #REF! | R47: 2º | S47: =Q47/$Q$51 -> #REF! | U47: Lockers | W47: =(S47+S56+S65)/3 -> #REF!
B48: Click&Collect | C48: =COUNTIF('City ​​of Madrid'!$C$4:$C$592,Datos!B48) -> 0 | D48: =COUNTIF('City ​​of Madrid'!$C$609:$C$770,Datos!B48) -> 0 | E48: =COUNTIF('City ​​of Madrid'!$C$772:$C$1323,Datos!B48) -> 0 | F48: =COUNTIF('City ​​of Madrid'!$C$1324:$C$1920,Datos!B48) -> 0 | G48: =COUNTIF('City ​​of Madrid'!$C$1927:$C$2045,Datos!B48) -> 0 | H48: =COUNTIF('City ​​of Madrid'!$C$2069:$C$2211,Datos!B48) -> 0 | I48: =COUNTIF('City ​​of Madrid'!$C$2227:$C$2621,Datos!B48) -> 0 | J48: =COUNTIF('City ​​of Madrid'!$C$2625:$C$2695,Datos!B48) -> 0 | K48: =COUNTIF('City ​​of Madrid'!$C$2764:$C$2773,Datos!B48) -> 0 | L48: =COUNTIF('City ​​of Madrid'!$C$2780:$C$2814,Datos!B48) -> 0 | M48: =COUNTIF('City ​​of Madrid'!$C$2923:$C$3100,Datos!B48) -> 0 | N48: =COUNTIF(#REF!,Datos!B48) -> #REF! | O48: =COUNTIF('City ​​of Madrid'!$C$3114:$C$3182,Datos!B48) -> 69 | P48: =COUNTIF('City ​​of Madrid'!$C$3260:$C$3267,Datos!B48) -> 0 | Q48: =SUM(C48:P48) -> #REF! | R48: 4º | S48: =Q48/$Q$51 -> #REF! | U48: Click&Collect | W48: =(S48+S57+S66)/3 -> #REF!
B49: LSP PUDOs | C49: =COUNTIF('City ​​of Madrid'!$C$4:$C$592,Datos!B49) -> 0 | D49: =COUNTIF('City ​​of Madrid'!$C$609:$C$770,Datos!B49) -> 89 | E49: =COUNTIF('City ​​of Madrid'!$C$772:$C$1323,Datos!B49) -> 0 | F49: =COUNTIF('City ​​of Madrid'!$C$1324:$C$1920,Datos!B49) -> 6 | G49: =COUNTIF('City ​​of Madrid'!$C$1927:$C$2045,Datos!B49) -> 8 | H49: =COUNTIF('City ​​of Madrid'!$C$2069:$C$2211,Datos!B49) -> 0 | I49: =COUNTIF('City ​​of Madrid'!$C$2227:$C$2621,Datos!B49) -> 0 | J49: =COUNTIF('City ​​of Madrid'!$C$2625:$C$2695,Datos!B49) -> 10 | K49: =COUNTIF('City ​​of Madrid'!$C$2764:$C$2773,Datos!B49) -> 10 | L49: =COUNTIF('City ​​of Madrid'!$C$2780:$C$2814,Datos!B49) -> 8 | M49: =COUNTIF('City ​​of Madrid'!$C$2923:$C$3100,Datos!B49) -> 0 | N49: =COUNTIF(#REF!,Datos!B49) -> #REF! | O49: =COUNTIF('City ​​of Madrid'!$C$3114:$C$3182,Datos!B49) -> 0 | P49: =COUNTIF('City ​​of Madrid'!$C$3260:$C$3267,Datos!B49) -> 8 | Q49: =SUM(C49:P49) -> #REF! | R49: 3º | S49: =Q49/$Q$51 -> #REF! | U49: LSP PUDOs | W49: =(S49+S58+S67)/3 -> #REF!
C51: =COUNTIF('City ​​of Madrid'!$B$4:B3267,Datos!C37) -> 589 | D51: =COUNTIF('City ​​of Madrid'!$B$4:B3267,Datos!D37) -> 178 | E51: =COUNTIF('City ​​of Madrid'!$B$4:B3267,Datos!E37) -> 553 | F51: =COUNTIF('City ​​of Madrid'!$B$4:B3267,Datos!F37) -> 597 | G51: =COUNTIF('City ​​of Madrid'!$B$4:B3267,Datos!G37) -> 125 | H51: =COUNTIF('City ​​of Madrid'!$B$4:B3267,Datos!H37) -> 181 | I51: =COUNTIF('City ​​of Madrid'!$B$4:B3267,Datos!I37) -> 398 | J51: =COUNTIF('City ​​of Madrid'!$B$4:B3267,Datos!J37) -> 139 | K51: =COUNTIF('City ​​of Madrid'!$B$4:B3267,Datos!K37) -> 16 | L51: =COUNTIF('City ​​of Madrid'!$B$4:B3267,Datos!L37) -> 93 | M51: =COUNTIF('City ​​of Madrid'!$B$4:B3267,Datos!M37) -> 241 | N51: =COUNTIF('City ​​of Madrid'!$B$4:B3267,Datos!N37) -> 0 | O51: =COUNTIF('City ​​of Madrid'!$B$4:B3267,Datos!O37) -> 146 | P51: =COUNTIF('City ​​of Madrid'!$B$4:B3267,Datos!P37) -> 8 | Q51: =SUM(C51:P51) -> 3264
B53: Valencia
B55: Convenience stores | C55: =COUNTIF('City ​​of Valencia'!$C$4:$C$101,Datos!B55) -> 81 | D55: =COUNTIF('City ​​of Valencia'!$C$102:$C$133,Datos!B55) -> 0 | E55: =COUNTIF('City ​​of Valencia'!$C$134:$C$349,Datos!B55) -> 157 | F55: =COUNTIF('City ​​of Valencia'!$C$350:$C$460,Datos!B55) -> 79 | G55: =COUNTIF('City ​​of Valencia'!$C$461:$C$517,Datos!B55) -> 53 | H55: =COUNTIF('City ​​of Valencia'!$C$518:$C$598,Datos!B55) -> 81 | I55: =COUNTIF('City ​​of Valencia'!$C$599:$C$772,Datos!B55) -> 174 | J55: =COUNTIF('City ​​of Valencia'!$C$773:$C$818,Datos!B55) -> 36 | K55: =COUNTIF('City ​​of Valencia'!$C$819:$C$823,Datos!B55) -> 0 | L55: =COUNTIF('City ​​of Valencia'!$C$824:$C$863,Datos!B55) -> 37 | M55: =COUNTIF('City ​​of Valencia'!$C$864:$C$952,Datos!B55) -> 79 | N55: 0 | O55: =COUNTIF('City ​​of Valencia'!$C$953:$C$976,Datos!B55) -> 0 | P55: =COUNTIF('City ​​of Valencia'!$C$977:$C$985,Datos!B55) -> 0 | Q55: =SUM(C55:P55) -> 777 | R55: 1º | S55: =Q55/$Q$60 -> 0.79124236
B56: Lockers | C56: =COUNTIF('City ​​of Valencia'!$C$4:$C$101,Datos!B56) -> 17 | D56: =COUNTIF('City ​​of Valencia'!$C$102:$C$133,Datos!B56) -> 28 | E56: =COUNTIF('City ​​of Valencia'!$C$134:$C$349,Datos!B56) -> 59 | F56: =COUNTIF('City ​​of Valencia'!$C$350:$C$460,Datos!B56) -> 19 | G56: =COUNTIF('City ​​of Valencia'!$C$461:$C$517,Datos!B56) -> 0 | H56: =COUNTIF('City ​​of Valencia'!$C$518:$C$598,Datos!B56) -> 0 | I56: =COUNTIF('City ​​of Valencia'!$C$599:$C$772,Datos!B56) -> 0 | J56: =COUNTIF('City ​​of Valencia'!$C$773:$C$818,Datos!B56) -> 0 | K56: =COUNTIF('City ​​of Valencia'!$C$819:$C$823,Datos!B56) -> 0 | L56: =COUNTIF('City ​​of Valencia'!$C$824:$C$863,Datos!B56) -> 0 | M56: =COUNTIF('City ​​of Valencia'!$C$864:$C$952,Datos!B56) -> 10 | N56: 0 | O56: =COUNTIF('City ​​of Valencia'!$C$953:$C$976,Datos!B56) -> 0 | P56: =COUNTIF('City ​​of Valencia'!$C$977:$C$985,Datos!B56) -> 0 | Q56: =SUM(C56:P56) -> 133 | R56: 2º | S56: =Q56/$Q$60 -> 0.13543788
B57: Click&Collect | C57: =COUNTIF('City ​​of Valencia'!$C$4:$C$101,Datos!B57) -> 0 | D57: =COUNTIF('City ​​of Valencia'!$C$102:$C$133,Datos!B57) -> 0 | E57: =COUNTIF('City ​​of Valencia'!$C$134:$C$349,Datos!B57) -> 0 | F57: =COUNTIF('City ​​of Valencia'!$C$350:$C$460,Datos!B57) -> 0 | G57: =COUNTIF('City ​​of Valencia'!$C$461:$C$517,Datos!B57) -> 0 | H57: =COUNTIF('City ​​of Valencia'!$C$518:$C$598,Datos!B57) -> 0 | I57: =COUNTIF('City ​​of Valencia'!$C$599:$C$772,Datos!B57) -> 0 | J57: =COUNTIF('City ​​of Valencia'!$C$773:$C$818,Datos!B57) -> 0 | K57: =COUNTIF('City ​​of Valencia'!$C$819:$C$823,Datos!B57) -> 0 | L57: =COUNTIF('City ​​of Valencia'!$C$824:$C$863,Datos!B57) -> 0 | M57: =COUNTIF('City ​​of Valencia'!$C$864:$C$952,Datos!B57) -> 0 | N57: 0 | O57: =COUNTIF('City ​​of Valencia'!$C$953:$C$976,Datos!B57) -> 24 | P57: =COUNTIF('City ​​of Valencia'!$C$977:$C$985,Datos!B57) -> 0 | Q57: =SUM(C57:P57) -> 24 | R57: 4º | S57: =Q57/$Q$60 -> 0.024439919
B58: LSP PUDOs | C58: =COUNTIF('City ​​of Valencia'!$C$4:$C$101,Datos!B58) -> 0 | D58: =COUNTIF('City ​​of Valencia'!$C$102:$C$133,Datos!B58) -> 4 | E58: =COUNTIF('City ​​of Valencia'!$C$134:$C$349,Datos!B58) -> 0 | F58: =COUNTIF('City ​​of Valencia'!$C$350:$C$460,Datos!B58) -> 13 | G58: =COUNTIF('City ​​of Valencia'!$C$461:$C$517,Datos!B58) -> 4 | H58: =COUNTIF('City ​​of Valencia'!$C$518:$C$598,Datos!B58) -> 0 | I58: =COUNTIF('City ​​of Valencia'!$C$599:$C$772,Datos!B58) -> 0 | J58: =COUNTIF('City ​​of Valencia'!$C$773:$C$818,Datos!B58) -> 10 | K58: =COUNTIF('City ​​of Valencia'!$C$819:$C$823,Datos!B58) -> 5 | L58: =COUNTIF('City ​​of Valencia'!$C$824:$C$863,Datos!B58) -> 3 | M58: =COUNTIF('City ​​of Valencia'!$C$864:$C$952,Datos!B58) -> 0 | N58: 0 | O58: =COUNTIF('City ​​of Valencia'!$C$953:$C$976,Datos!B58) -> 0 | P58: =COUNTIF('City ​​of Valencia'!$C$977:$C$985,Datos!B58) -> 9 | Q58: =SUM(C58:P58) -> 48 | R58: 3º | S58: =Q58/$Q$60 -> 0.048879837
C60: =COUNTIF('City ​​of Valencia'!$B$4:B985,Datos!C37) -> 98 | D60: =COUNTIF('City ​​of Valencia'!$B$4:B985,Datos!D37) -> 32 | E60: =COUNTIF('City ​​of Valencia'!$B$4:B985,Datos!E37) -> 216 | F60: =COUNTIF('City ​​of Valencia'!$B$4:B985,Datos!F37) -> 111 | G60: =COUNTIF('City ​​of Valencia'!$B$4:B985,Datos!G37) -> 57 | H60: =COUNTIF('City ​​of Valencia'!$B$4:B985,Datos!H37) -> 81 | I60: =COUNTIF('City ​​of Valencia'!$B$4:B985,Datos!I37) -> 174 | J60: =COUNTIF('City ​​of Valencia'!$B$4:B985,Datos!J37) -> 46 | K60: =COUNTIF('City ​​of Valencia'!$B$4:B985,Datos!K37) -> 5 | L60: =COUNTIF('City ​​of Valencia'!$B$4:B985,Datos!L37) -> 40 | M60: =COUNTIF('City ​​of Valencia'!$B$4:B985,Datos!M37) -> 89 | N60: =COUNTIF('City ​​of Valencia'!$B$4:B985,Datos!N37) -> 0 | O60: =COUNTIF('City ​​of Valencia'!$B$4:B985,Datos!O37) -> 24 | P60: =COUNTIF('City ​​of Valencia'!$B$4:B985,Datos!P37) -> 9 | Q60: =SUM(C60:P60) -> 982
B62: Barcelona
B64: Convenience stores | C64: =COUNTIF('City ​​of Barcelona'!$C$4:$C$361,Datos!B64) -> 273 | D64: =COUNTIF('City ​​of Barcelona'!$C$439:$C$504,Datos!B64) -> 0 | E64: =COUNTIF('City ​​of Barcelona'!$C$529:$C$852,Datos!B64) -> 130 | F64: =COUNTIF('City ​​of Barcelona'!$C$951:$C$1267,Datos!B64) -> 201 | G64: =COUNTIF('City ​​of Barcelona'!$C$1312:$C$1406,Datos!B64) -> 90 | H64: =COUNTIF('City ​​of Barcelona'!$C$1420:$C$1514,Datos!B64) -> 95 | I64: =COUNTIF('City ​​of Barcelona'!$C$1530:$C$1743,Datos!B64) -> 214 | J64: =COUNTIF('City ​​of Barcelona'!$C$1825:$C$1869,Datos!B64) -> 35 | K64: =COUNTIF('City ​​of Barcelona'!$C$1884:$C$1906,Datos!B64) -> 0 | L64: =COUNTIF('City ​​of Barcelona'!$C$1911:$C$1967,Datos!B64) -> 46 | M64: =COUNTIF('City ​​of Barcelona'!$C$1988:$C$2145,Datos!B64) -> 158 | N64: 0 | O64: =COUNTIF('City ​​of Barcelona'!$C$2176:$C$2259,Datos!B64) -> 0 | P64: =COUNTIF('City ​​of Barcelona'!$C$2273:$C$2285,Datos!B64) -> 0 | Q64: =SUM(C64:P64) -> 1242 | R64: 1º | S64: =Q64/$Q$69 -> 0.54425942
B65: Lockers | C65: =COUNTIF('City ​​of Barcelona'!$C$4:$C$361,Datos!B65) -> 85 | D65: =COUNTIF('City ​​of Barcelona'!$C$439:$C$504,Datos!B65) -> 48 | E65: =COUNTIF('City ​​of Barcelona'!$C$529:$C$852,Datos!B65) -> 194 | F65: =COUNTIF('City ​​of Barcelona'!$C$951:$C$1267,Datos!B65) -> 113 | G65: =COUNTIF('City ​​of Barcelona'!$C$1312:$C$1406,Datos!B65) -> 0 | H65: =COUNTIF('City ​​of Barcelona'!$C$1420:$C$1514,Datos!B65) -> 0 | I65: =COUNTIF('City ​​of Barcelona'!$C$1530:$C$1743,Datos!B65) -> 0 | J65: =COUNTIF('City ​​of Barcelona'!$C$1825:$C$1869,Datos!B65) -> 0 | K65: =COUNTIF('City ​​of Barcelona'!$C$1884:$C$1906,Datos!B65) -> 0 | L65: =COUNTIF('City ​​of Barcelona'!$C$1911:$C$1967,Datos!B65) -> 0 | M65: =COUNTIF('City ​​of Barcelona'!$C$1988:$C$2145,Datos!B65) -> 0 | N65: 0 | O65: =COUNTIF('City ​​of Barcelona'!$C$2176:$C$2259,Datos!B65) -> 0 | P65: =COUNTIF('City ​​of Barcelona'!$C$2273:$C$2285,Datos!B65) -> 0 | Q65: =SUM(C65:P65) -> 440 | R65: 2º | S65: =Q65/$Q$69 -> 0.19281332
B66: Click&Collect | C66: =COUNTIF('City ​​of Barcelona'!$C$4:$C$361,Datos!B66) -> 0 | D66: =COUNTIF('City ​​of Barcelona'!$C$439:$C$504,Datos!B66) -> 0 | E66: =COUNTIF('City ​​of Barcelona'!$C$529:$C$852,Datos!B66) -> 0 | F66: =COUNTIF('City ​​of Barcelona'!$C$951:$C$1267,Datos!B66) -> 0 | G66: =COUNTIF('City ​​of Barcelona'!$C$1312:$C$1406,Datos!B66) -> 0 | H66: =COUNTIF('City ​​of Barcelona'!$C$1420:$C$1514,Datos!B66) -> 0 | I66: =COUNTIF('City ​​of Barcelona'!$C$1530:$C$1743,Datos!B66) -> 0 | J66: =COUNTIF('City ​​of Barcelona'!$C$1825:$C$1869,Datos!B66) -> 0 | K66: =COUNTIF('City ​​of Barcelona'!$C$1884:$C$1906,Datos!B66) -> 0 | L66: =COUNTIF('City ​​of Barcelona'!$C$1911:$C$1967,Datos!B66) -> 0 | M66: =COUNTIF('City ​​of Barcelona'!$C$1988:$C$2145,Datos!B66) -> 0 | N66: 0 | O66: =COUNTIF('City ​​of Barcelona'!$C$2176:$C$2259,Datos!B66) -> 84 | P66: =COUNTIF('City ​​of Barcelona'!$C$2273:$C$2285,Datos!B66) -> 0 | Q66: =SUM(C66:P66) -> 84 | R66: 3º | S66: =Q66/$Q$69 -> 0.036809816
B67: LSP PUDOs | C67: =COUNTIF('City ​​of Barcelona'!$C$4:$C$361,Datos!B67) -> 0 | D67: =COUNTIF('City ​​of Barcelona'!$C$439:$C$504,Datos!B67) -> 18 | E67: =COUNTIF('City ​​of Barcelona'!$C$529:$C$852,Datos!B67) -> 0 | F67: =COUNTIF('City ​​of Barcelona'!$C$951:$C$1267,Datos!B67) -> 3 | G67: =COUNTIF('City ​​of Barcelona'!$C$1312:$C$1406,Datos!B67) -> 5 | H67: =COUNTIF('City ​​of Barcelona'!$C$1420:$C$1514,Datos!B67) -> 0 | I67: =COUNTIF('City ​​of Barcelona'!$C$1530:$C$1743,Datos!B67) -> 0 | J67: =COUNTIF('City ​​of Barcelona'!$C$1825:$C$1869,Datos!B67) -> 10 | K67: =COUNTIF('City ​​of Barcelona'!$C$1884:$C$1906,Datos!B67) -> 23 | L67: =COUNTIF('City ​​of Barcelona'!$C$1911:$C$1967,Datos!B67) -> 11 | M67: =COUNTIF('City ​​of Barcelona'!$C$1988:$C$2145,Datos!B67) -> 0 | N67: 0 | O67: =COUNTIF('City ​​of Barcelona'!$C$2176:$C$2259,Datos!B67) -> 0 | P67: =COUNTIF('City ​​of Barcelona'!$C$2273:$C$2285,Datos!B67) -> 13 | Q67: =SUM(C67:P67) -> 83 | R67: 4º | S67: =Q67/$Q$69 -> 0.036371604
C69: =COUNTIF('City ​​of Barcelona'!$B$4:B2285,Datos!C37) -> 435 | D69: =COUNTIF('City ​​of Barcelona'!$B$4:B2285,Datos!D37) -> 90 | E69: =COUNTIF('City ​​of Barcelona'!$B$4:B2285,Datos!E37) -> 422 | F69: =COUNTIF('City ​​of Barcelona'!$B$4:B2285,Datos!F37) -> 361 | G69: =COUNTIF('City ​​of Barcelona'!$B$4:B2285,Datos!G37) -> 108 | H69: =COUNTIF('City ​​of Barcelona'!$B$4:B2285,Datos!H37) -> 110 | I69: =COUNTIF('City ​​of Barcelona'!$B$4:B2285,Datos!I37) -> 295 | J69: =COUNTIF('City ​​of Barcelona'!$B$4:B2285,Datos!J37) -> 59 | K69: =COUNTIF('City ​​of Barcelona'!$B$4:B2285,Datos!K37) -> 27 | L69: =COUNTIF('City ​​of Barcelona'!$B$4:B2285,Datos!L37) -> 77 | M69: =COUNTIF('City ​​of Barcelona'!$B$4:B2285,Datos!M37) -> 188 | N69: =COUNTIF('City ​​of Barcelona'!$B$4:B2285,Datos!N37) -> 0 | O69: =COUNTIF('City ​​of Barcelona'!$B$4:B2285,Datos!O37) -> 97 | P69: =COUNTIF('City ​​of Barcelona'!$B$4:B2285,Datos!P37) -> 13 | Q69: =SUM(C69:P69) -> 2282
B73: Totales
B75: Convenience stores | C75: =C46+C55+C64 -> 817 | D75: =D46+D55+D64 -> 0 | E75: =E46+E55+E64 -> 591 | F75: =F46+F55+F64 -> 654 | G75: =G46+G55+G64 -> 254 | H75: =H46+H55+H64 -> 319 | I75: =I46+I55+I64 -> 783 | J75: =J46+J55+J64 -> 130 | ... P75: =P46+P55+P64 -> 0 | Q75: =SUM(C75:P75) -> #REF! | R75: 1º | S75: =Q75/$Q$80 -> #REF!
B76: Lockers | C76: =C47+C56+C65 -> 227 | D76: =D47+D56+D65 -> 149 | E76: =E47+E56+E65 -> 501 | F76: =F47+F56+F65 -> 349 | G76: =G47+G56+G65 -> 0 | H76: =H47+H56+H65 -> 0 | I76: =I47+I56+I65 -> 0 | J76: =J47+J56+J65 -> 2 | ... P76: =P47+P56+P65 -> 0 | Q76: =SUM(C76:P76) -> #REF! | R76: 2º | S76: =Q76/$Q$80 -> #REF!
B77: Click&Collect | C77: =C48+C57+C66 -> 0 | D77: =D48+D57+D66 -> 0 | E77: =E48+E57+E66 -> 0 | F77: =F48+F57+F66 -> 0 | G77: =G48+G57+G66 -> 0 | H77: =H48+H57+H66 -> 0 | I77: =I48+I57+I66 -> 0 | J77: =J48+J57+J66 -> 0 | ... P77: =P48+P57+P66 -> 0 | Q77: =SUM(C77:P77) -> #REF! | R77: 4º | S77: =Q77/$Q$80 -> #REF!
B78: LSP PUDOs | C78: =C49+C58+C67 -> 0 | D78: =D49+D58+D67 -> 111 | E78: =E49+E58+E67 -> 0 | F78: =F49+F58+F67 -> 22 | G78: =G49+G58+G67 -> 17 | H78: =H49+H58+H67 -> 0 | I78: =I49+I58+I67 -> 0 | J78: =J49+J58+J67 -> 30 | ... P78: =P49+P58+P67 -> 30 | Q78: =SUM(C78:P78) -> #REF! | R78: 3º | S78: =Q78/$Q$80 -> #REF!
Q80: =SUM(Q75:Q78) -> #REF!
